{
  "paper_id": "2019_1047",
  "references": [
    {
      "key": "[Abd+19]",
      "raw_text": "B. Abdolmaleki, K. Baghery, H. Lipmaa, J. Siim, and M. Zajac. UC-Secure CRS Generation for SNARKs. In: AFRICACRYPT '19. 2019, pp. 99-117.",
      "authors": [
        "Abdolmaleki, B.",
        "Baghery, K.",
        "Lipmaa, H.",
        "Siim, J.",
        "Zajac, M."
      ],
      "title": "UC-Secure CRS Generation for SNARKs",
      "year": "2019",
      "venue": "AFRICACRYPT 2019",
      "volume": "",
      "pages": "99-117",
      "doi": "",
      "urls": [],
      "eprint_id": "",
      "arxiv_id": "",
      "isbn": "",
      "note": "",
      "entry_type": "inproceedings",
      "alpha_key": "ABL+19"
    },
    {
      "key": "[Ame+17]",
      "raw_text": "S. Ames, C. Hazay, Y. Ishai, and M. Venkitasubramaniam. Ligero: Lightweight Sublinear Arguments Without a Trusted Setup. In: CCS '17. 2017, pp. 2087-2104.",
      "authors": [
        "Ames, S.",
        "Hazay, C.",
        "Ishai, Y.",
        "Venkitasubramaniam, M."
      ],
      "title": "Ligero: Lightweight Sublinear Arguments Without a Trusted Setup",
      "year": "2017",
      "venue": "ACM CCS 2017",
      "volume": "",
      "pages": "2087-2104",
      "doi": "",
      "urls": [],
      "eprint_id": "",
      "arxiv_id": "",
      "isbn": "",
      "note": "",
      "entry_type": "inproceedings",
      "alpha_key": "AHIV17"
    },
    {
      "key": "[Aro+98]",
      "raw_text": "S. Arora, C. Lund, R. Motwani, M. Sudan, and M. Szegedy. Proof verification and the hardness of approximation problems. In: Journal of the ACM 45.3 (1998), pp. 501-555.",
      "authors": [
        "Arora, S.",
        "Lund, C.",
        "Motwani, R.",
        "Sudan, M.",
        "Szegedy, M."
      ],
      "title": "Proof verification and the hardness of approximation problems",
      "year": "1998",
      "venue": "Journal of the ACM",
      "volume": "45(3)",
      "pages": "501-555",
      "doi": "",
      "urls": [],
      "eprint_id": "",
      "arxiv_id": "",
      "isbn": "",
      "note": "Preliminary version in FOCS 1992",
      "entry_type": "article",
      "alpha_key": "ALM+98"
    },
    {
      "key": "[AS98]",
      "raw_text": "S. Arora and S. Safra. Probabilistic checking of proofs: a new characterization of NP. In: Journal of the ACM 45.1 (1998), pp. 70-122.",
      "authors": [
        "Arora, S.",
        "Safra, S."
      ],
      "title": "Probabilistic checking of proofs: a new characterization of NP",
      "year": "1998",
      "venue": "Journal of the ACM",
      "volume": "45(1)",
      "pages": "70-122",
      "doi": "",
      "urls": [],
      "eprint_id": "",
      "arxiv_id": "",
      "isbn": "",
      "note": "Preliminary version in FOCS 1992",
      "entry_type": "article",
      "alpha_key": "AS98"
    },
    {
      "key": "[Bab85]",
      "raw_text": "L. Babai. Trading group theory for randomness. In: STOC '85. 1985, pp. 421-429.",
      "authors": [
        "Babai, L."
      ],
      "title": "Trading group theory for randomness",
      "year": "1985",
      "venue": "STOC 1985",
      "volume": "",
      "pages": "421-429",
      "doi": "",
      "urls": [],
      "eprint_id": "",
      "arxiv_id": "",
      "isbn": "",
      "note": "",
      "entry_type": "inproceedings",
      "alpha_key": "Bab85"
    },
    {
      "key": "[Bab+91]",
      "raw_text": "L. Babai, L. Fortnow, L. A. Levin, and M. Szegedy. Checking computations in polylogarithmic time. In: STOC '91. 1991, pp. 21-32.",
      "authors": [
        "Babai, L.",
        "Fortnow, L.",
        "Levin, L. A.",
        "Szegedy, M."
      ],
      "title": "Checking computations in polylogarithmic time",
      "year": "1991",
      "venue": "STOC 1991",
      "volume": "",
      "pages": "21-32",
      "doi": "",
      "urls": [],
      "eprint_id": "",
      "arxiv_id": "",
      "isbn": "",
      "note": "",
      "entry_type": "inproceedings",
      "alpha_key": "BFLS91"
    },
    {
      "key": "[BB04]",
      "raw_text": "D. Boneh and X. Boyen. Short Signatures Without Random Oracles. In: EUROCRYPT '04. 2004, pp. 56-73.",
      "authors": [
        "Boneh, D.",
        "Boyen, X."
      ],
      "title": "Short Signatures Without Random Oracles",
      "year": "2004",
      "venue": "EUROCRYPT 2004",
      "volume": "",
      "pages": "56-73",
      "doi": "",
      "urls": [],
      "eprint_id": "",
      "arxiv_id": "",
      "isbn": "",
      "note": "",
      "entry_type": "inproceedings",
      "alpha_key": "BB04"
    },
    {
      "key": "[BCC88]",
      "raw_text": "G. Brassard, D. Chaum, and C. Crepeau. Minimum disclosure proofs of knowledge. In: Journal of Computer and System Sciences 37.2 (1988), pp. 156-189.",
      "authors": [
        "Brassard, G.",
        "Chaum, D.",
        "Crepeau, C."
      ],
      "title": "Minimum disclosure proofs of knowledge",
      "year": "1988",
      "venue": "Journal of Computer and System Sciences",
      "volume": "37(2)",
      "pages": "156-189",
      "doi": "",
      "urls": [],
      "eprint_id": "",
      "arxiv_id": "",
      "isbn": "",
      "note": "",
      "entry_type": "article",
      "alpha_key": "BCC88"
    },
    {
      "key": "[BCS16]",
      "raw_text": "E. Ben-Sasson, A. Chiesa, and N. Spooner. Interactive Oracle Proofs. In: TCC '16-B. 2016, pp. 31-60.",
      "authors": [
        "Ben-Sasson, E.",
        "Chiesa, A.",
        "Spooner, N."
      ],
      "title": "Interactive Oracle Proofs",
      "year": "2016",
      "venue": "TCC 2016-B",
      "volume": "",
      "pages": "31-60",
      "doi": "",
      "urls": [],
      "eprint_id": "",
      "arxiv_id": "",
      "isbn": "",
      "note": "",
      "entry_type": "inproceedings",
      "alpha_key": "BSCS16"
    },
    {
      "key": "[Ben+14a]",
      "raw_text": "E. Ben-Sasson, A. Chiesa, E. Tromer, and M. Virza. Scalable Zero Knowledge via Cycles of Elliptic Curves. In: CRYPTO '14. 2014, pp. 276-294.",
      "authors": [
        "Ben-Sasson, E.",
        "Chiesa, A.",
        "Tromer, E.",
        "Virza, M."
      ],
      "title": "Scalable Zero Knowledge via Cycles of Elliptic Curves",
      "year": "2014",
      "venue": "CRYPTO 2014",
      "volume": "",
      "pages": "276-294",
      "doi": "",
      "urls": [
        "http://eprint.iacr.org/2014/595"
      ],
      "eprint_id": "2014/595",
      "arxiv_id": "",
      "isbn": "",
      "note": "",
      "entry_type": "inproceedings",
      "alpha_key": "BSCTV14"
    },
    {
      "key": "[Ben+14b]",
      "raw_text": "E. Ben-Sasson, A. Chiesa, E. Tromer, and M. Virza. Succinct Non-Interactive Zero Knowledge for a von Neumann Architecture. In: USENIX Security '14. 2014, pp. 781-796.",
      "authors": [
        "Ben-Sasson, E.",
        "Chiesa, A.",
        "Tromer, E.",
        "Virza, M."
      ],
      "title": "Succinct Non-Interactive Zero Knowledge for a von Neumann Architecture",
      "year": "2014",
      "venue": "USENIX Security 2014",
      "volume": "",
      "pages": "781-796",
      "doi": "",
      "urls": [
        "http://eprint.iacr.org/2013/879"
      ],
      "eprint_id": "2013/879",
      "arxiv_id": "",
      "isbn": "",
      "note": "",
      "entry_type": "inproceedings",
      "alpha_key": "BSCTV14"
    },
    {
      "key": "[Ben+15]",
      "raw_text": "E. Ben-Sasson, A. Chiesa, M. Green, E. Tromer, and M. Virza. Secure Sampling of Public Parameters for Succinct Zero Knowledge Proofs. In: S&P '15. 2015, pp. 287-304.",
      "authors": [
        "Ben-Sasson, E.",
        "Chiesa, A.",
        "Green, M.",
        "Tromer, E.",
        "Virza, M."
      ],
      "title": "Secure Sampling of Public Parameters for Succinct Zero Knowledge Proofs",
      "year": "2015",
      "venue": "IEEE S&P 2015",
      "volume": "",
      "pages": "287-304",
      "doi": "",
      "urls": [],
      "eprint_id": "",
      "arxiv_id": "",
      "isbn": "",
      "note": "",
      "entry_type": "inproceedings",
      "alpha_key": "BSCG+15"
    },
    {
      "key": "[Ben+16]",
      "raw_text": "E. Ben-Sasson, A. Chiesa, A. Gabizon, and M. Virza. Quasilinear-Size Zero Knowledge from Linear-Algebraic PCPs. In: TCC '16-A. 2016, pp. 33-64.",
      "authors": [
        "Ben-Sasson, E.",
        "Chiesa, A.",
        "Gabizon, A.",
        "Virza, M."
      ],
      "title": "Quasilinear-Size Zero Knowledge from Linear-Algebraic PCPs",
      "year": "2016",
      "venue": "TCC 2016-A",
      "volume": "",
      "pages": "33-64",
      "doi": "",
      "urls": [],
      "eprint_id": "",
      "arxiv_id": "",
      "isbn": "",
      "note": "",
      "entry_type": "inproceedings",
      "alpha_key": "BSCGV16"
    },
    {
      "key": "[Ben+17a]",
      "raw_text": "E. Ben-Sasson, A. Chiesa, A. Gabizon, M. Riabzev, and N. Spooner. Interactive Oracle Proofs with Constant Rate and Query Complexity. In: ICALP '17. 2017, 40:1-40:15.",
      "authors": [
        "Ben-Sasson, E.",
        "Chiesa, A.",
        "Gabizon, A.",
        "Riabzev, M.",
        "Spooner, N."
      ],
      "title": "Interactive Oracle Proofs with Constant Rate and Query Complexity",
      "year": "2017",
      "venue": "ICALP 2017",
      "volume": "",
      "pages": "40:1-40:15",
      "doi": "",
      "urls": [],
      "eprint_id": "",
      "arxiv_id": "",
      "isbn": "",
      "note": "",
      "entry_type": "inproceedings",
      "alpha_key": "BSCG+17"
    },
    {
      "key": "[Ben+17b]",
      "raw_text": "E. Ben-Sasson et al. Computational integrity with a public random string from quasi-linear PCPs. In: EUROCRYPT '17. 2017, pp. 551-579.",
      "authors": [
        "Ben-Sasson, E.",
        "et al."
      ],
      "title": "Computational integrity with a public random string from quasi-linear PCPs",
      "year": "2017",
      "venue": "EUROCRYPT 2017",
      "volume": "",
      "pages": "551-579",
      "doi": "",
      "urls": [],
      "eprint_id": "",
      "arxiv_id": "",
      "isbn": "",
      "note": "",
      "entry_type": "inproceedings",
      "alpha_key": "BSeal17"
    },
    {
      "key": "[Ben+19a]",
      "raw_text": "E. Ben-Sasson, I. Bentov, Y. Horesh, and M. Riabzev. Scalable Zero Knowledge with No Trusted Setup. In: CRYPTO '19. 2019, pp. 733-764.",
      "authors": [
        "Ben-Sasson, E.",
        "Bentov, I.",
        "Horesh, Y.",
        "Riabzev, M."
      ],
      "title": "Scalable Zero Knowledge with No Trusted Setup",
      "year": "2019",
      "venue": "CRYPTO 2019",
      "volume": "",
      "pages": "733-764",
      "doi": "",
      "urls": [],
      "eprint_id": "",
      "arxiv_id": "",
      "isbn": "",
      "note": "",
      "entry_type": "inproceedings",
      "alpha_key": "BSBHR19"
    },
    {
      "key": "[Ben+19b]",
      "raw_text": "E. Ben-Sasson, A. Chiesa, L. Goldberg, T. Gur, M. Riabzev, and N. Spooner. Linear-Size Constant-Query IOPs for Delegating Computation. In: TCC '19. 2019.",
      "authors": [
        "Ben-Sasson, E.",
        "Chiesa, A.",
        "Goldberg, L.",
        "Gur, T.",
        "Riabzev, M.",
        "Spooner, N."
      ],
      "title": "Linear-Size Constant-Query IOPs for Delegating Computation",
      "year": "2019",
      "venue": "TCC 2019",
      "volume": "",
      "pages": "",
      "doi": "",
      "urls": [],
      "eprint_id": "",
      "arxiv_id": "",
      "isbn": "",
      "note": "",
      "entry_type": "inproceedings",
      "alpha_key": "BSCG+19"
    },
    {
      "key": "[Ben+19c]",
      "raw_text": "E. Ben-Sasson, A. Chiesa, M. Riabzev, N. Spooner, M. Virza, and N. P. Ward. Aurora: Transparent Succinct Arguments for R1CS. In: EUROCRYPT '19. 2019, pp. 103-128.",
      "authors": [
        "Ben-Sasson, E.",
        "Chiesa, A.",
        "Riabzev, M.",
        "Spooner, N.",
        "Virza, M.",
        "Ward, N. P."
      ],
      "title": "Aurora: Transparent Succinct Arguments for R1CS",
      "year": "2019",
      "venue": "EUROCRYPT 2019",
      "volume": "",
      "pages": "103-128",
      "doi": "",
      "urls": [
        "https://eprint.iacr.org/2018/828"
      ],
      "eprint_id": "2018/828",
      "arxiv_id": "",
      "isbn": "",
      "note": "",
      "entry_type": "inproceedings",
      "alpha_key": "BSCR+19"
    },
    {
      "key": "[BG04]",
      "raw_text": "D. R. L. Brown and R. P. Gallant. The Static Diffie-Hellman Problem. Cryptology ePrint Archive, Report 2004/306. 2004.",
      "authors": [
        "Brown, D. R. L.",
        "Gallant, R. P."
      ],
      "title": "The Static Diffie-Hellman Problem",
      "year": "2004",
      "venue": "Cryptology ePrint Archive",
      "volume": "",
      "pages": "",
      "doi": "",
      "urls": [],
      "eprint_id": "2004/306",
      "arxiv_id": "",
      "isbn": "",
      "note": "Report 2004/306",
      "entry_type": "techreport",
      "alpha_key": "BG04"
    },
    {
      "key": "[BG12]",
      "raw_text": "S. Bayer and J. Groth. Efficient Zero-Knowledge Argument for Correctness of a Shuffle. In: EUROCRYPT '12. 2012, pp. 263-280.",
      "authors": [
        "Bayer, S.",
        "Groth, J."
      ],
      "title": "Efficient Zero-Knowledge Argument for Correctness of a Shuffle",
      "year": "2012",
      "venue": "EUROCRYPT 2012",
      "volume": "",
      "pages": "263-280",
      "doi": "",
      "urls": [],
      "eprint_id": "",
      "arxiv_id": "",
      "isbn": "",
      "note": "",
      "entry_type": "inproceedings",
      "alpha_key": "BG12"
    },
    {
      "key": "[BGG17]",
      "raw_text": "S. Bowe, A. Gabizon, and M. Green. A multi-party protocol for constructing the public parameters of the Pinocchio zk-SNARK. Cryptology ePrint Archive, Report 2017/602. 2017.",
      "authors": [
        "Bowe, S.",
        "Gabizon, A.",
        "Green, M."
      ],
      "title": "A multi-party protocol for constructing the public parameters of the Pinocchio zk-SNARK",
      "year": "2017",
      "venue": "Cryptology ePrint Archive",
      "volume": "",
      "pages": "",
      "doi": "",
      "urls": [],
      "eprint_id": "2017/602",
      "arxiv_id": "",
      "isbn": "",
      "note": "Report 2017/602",
      "entry_type": "techreport",
      "alpha_key": "BGG17"
    },
    {
      "key": "[BGM17]",
      "raw_text": "S. Bowe, A. Gabizon, and I. Miers. Scalable Multi-party Computation for zk-SNARK Parameters in the Random Beacon Model. Cryptology ePrint Archive, Report 2017/1050. 2017.",
      "authors": [
        "Bowe, S.",
        "Gabizon, A.",
        "Miers, I."
      ],
      "title": "Scalable Multi-party Computation for zk-SNARK Parameters in the Random Beacon Model",
      "year": "2017",
      "venue": "Cryptology ePrint Archive",
      "volume": "",
      "pages": "",
      "doi": "",
      "urls": [],
      "eprint_id": "2017/1050",
      "arxiv_id": "",
      "isbn": "",
      "note": "Report 2017/1050",
      "entry_type": "techreport",
      "alpha_key": "BGM17"
    },
    {
      "key": "[Bit+13]",
      "raw_text": "N. Bitansky, A. Chiesa, Y. Ishai, R. Ostrovsky, and O. Paneth. Succinct Non-Interactive Arguments via Linear Interactive Proofs. In: TCC '13. 2013, pp. 315-333.",
      "authors": [
        "Bitansky, N.",
        "Chiesa, A.",
        "Ishai, Y.",
        "Ostrovsky, R.",
        "Paneth, O."
      ],
      "title": "Succinct Non-Interactive Arguments via Linear Interactive Proofs",
      "year": "2013",
      "venue": "TCC 2013",
      "volume": "",
      "pages": "315-333",
      "doi": "",
      "urls": [],
      "eprint_id": "",
      "arxiv_id": "",
      "isbn": "",
      "note": "",
      "entry_type": "inproceedings",
      "alpha_key": "BCI+13"
    },
    {
      "key": "[Bit+16]",
      "raw_text": "N. Bitansky, R. Canetti, O. Paneth, and A. Rosen. On the Existence of Extractable One-Way Functions. In: SIAM Journal on Computing 45.5 (2016), pp. 1910-1952.",
      "authors": [
        "Bitansky, N.",
        "Canetti, R.",
        "Paneth, O.",
        "Rosen, A."
      ],
      "title": "On the Existence of Extractable One-Way Functions",
      "year": "2016",
      "venue": "SIAM Journal on Computing",
      "volume": "45(5)",
      "pages": "1910-1952",
      "doi": "",
      "urls": [],
      "eprint_id": "",
      "arxiv_id": "",
      "isbn": "",
      "note": "Preliminary version in STOC 2014",
      "entry_type": "article",
      "alpha_key": "BCPR16"
    },
    {
      "key": "[Bon+17]",
      "raw_text": "D. Boneh, Y. Ishai, A. Sahai, and D. J. Wu. Lattice-Based SNARGs and Their Application to More Efficient Obfuscation. In: EUROCRYPT '17. 2017, pp. 247-277.",
      "authors": [
        "Boneh, D.",
        "Ishai, Y.",
        "Sahai, A.",
        "Wu, D. J."
      ],
      "title": "Lattice-Based SNARGs and Their Application to More Efficient Obfuscation",
      "year": "2017",
      "venue": "EUROCRYPT 2017",
      "volume": "",
      "pages": "247-277",
      "doi": "",
      "urls": [],
      "eprint_id": "",
      "arxiv_id": "",
      "isbn": "",
      "note": "",
      "entry_type": "inproceedings",
      "alpha_key": "BISW17"
    },
    {
      "key": "[Bon+18]",
      "raw_text": "D. Boneh, Y. Ishai, A. Sahai, and D. J. Wu. Quasi-Optimal SNARGs via Linear Multi-Prover Interactive Proofs. In: EUROCRYPT '18. 2018, pp. 222-255.",
      "authors": [
        "Boneh, D.",
        "Ishai, Y.",
        "Sahai, A.",
        "Wu, D. J."
      ],
      "title": "Quasi-Optimal SNARGs via Linear Multi-Prover Interactive Proofs",
      "year": "2018",
      "venue": "EUROCRYPT 2018",
      "volume": "",
      "pages": "222-255",
      "doi": "",
      "urls": [],
      "eprint_id": "",
      "arxiv_id": "",
      "isbn": "",
      "note": "",
      "entry_type": "inproceedings",
      "alpha_key": "BISW18"
    },
    {
      "key": "[Boo+16]",
      "raw_text": "J. Bootle, A. Cerulli, P. Chaidos, J. Groth, and C. Petit. Efficient Zero-Knowledge Arguments for Arithmetic Circuits in the Discrete Log Setting. In: EUROCRYPT '16. 2016, pp. 327-357.",
      "authors": [
        "Bootle, J.",
        "Cerulli, A.",
        "Chaidos, P.",
        "Groth, J.",
        "Petit, C."
      ],
      "title": "Efficient Zero-Knowledge Arguments for Arithmetic Circuits in the Discrete Log Setting",
      "year": "2016",
      "venue": "EUROCRYPT 2016",
      "volume": "",
      "pages": "327-357",
      "doi": "",
      "urls": [],
      "eprint_id": "",
      "arxiv_id": "",
      "isbn": "",
      "note": "",
      "entry_type": "inproceedings",
      "alpha_key": "BCC+16"
    },
    {
      "key": "[BP15]",
      "raw_text": "E. Boyle and R. Pass. Limits of Extractability Assumptions with Distributional Auxiliary Input. In: ASIACRYPT '15. 2015, pp. 236-261.",
      "authors": [
        "Boyle, E.",
        "Pass, R."
      ],
      "title": "Limits of Extractability Assumptions with Distributional Auxiliary Input",
      "year": "2015",
      "venue": "ASIACRYPT 2015",
      "volume": "",
      "pages": "236-261",
      "doi": "",
      "urls": [],
      "eprint_id": "",
      "arxiv_id": "",
      "isbn": "",
      "note": "",
      "entry_type": "inproceedings",
      "alpha_key": "BP15"
    },
    {
      "key": "[BS08]",
      "raw_text": "E. Ben-Sasson and M. Sudan. Short PCPs with Polylog Query Complexity. In: SIAM Journal on Computing 38.2 (2008), pp. 551-607.",
      "authors": [
        "Ben-Sasson, E.",
        "Sudan, M."
      ],
      "title": "Short PCPs with Polylog Query Complexity",
      "year": "2008",
      "venue": "SIAM Journal on Computing",
      "volume": "38(2)",
      "pages": "551-607",
      "doi": "",
      "urls": [],
      "eprint_id": "",
      "arxiv_id": "",
      "isbn": "",
      "note": "Preliminary version in STOC 2005",
      "entry_type": "article",
      "alpha_key": "BSS08"
    },
    {
      "key": "[Bun+18]",
      "raw_text": "B. Bunz, J. Bootle, D. Boneh, A. Poelstra, P. Wuille, and G. Maxwell. Bulletproofs: Short Proofs for Confidential Transactions and More. In: S&P '18. 2018, pp. 315-334.",
      "authors": [
        "Bunz, B.",
        "Bootle, J.",
        "Boneh, D.",
        "Poelstra, A.",
        "Wuille, P.",
        "Maxwell, G."
      ],
      "title": "Bulletproofs: Short Proofs for Confidential Transactions and More",
      "year": "2018",
      "venue": "IEEE S&P 2018",
      "volume": "",
      "pages": "315-334",
      "doi": "",
      "urls": [],
      "eprint_id": "",
      "arxiv_id": "",
      "isbn": "",
      "note": "",
      "entry_type": "inproceedings",
      "alpha_key": "BBB+18"
    },
    {
      "key": "[CD98]",
      "raw_text": "R. Cramer and I. Damgard. Zero-Knowledge Proofs for Finite Field Arithmetic; or: Can Zero-Knowledge be for Free? In: CRYPTO '98. 1998, pp. 424-441.",
      "authors": [
        "Cramer, R.",
        "Damgard, I."
      ],
      "title": "Zero-Knowledge Proofs for Finite Field Arithmetic; or: Can Zero-Knowledge be for Free?",
      "year": "1998",
      "venue": "CRYPTO 1998",
      "volume": "",
      "pages": "424-441",
      "doi": "",
      "urls": [],
      "eprint_id": "",
      "arxiv_id": "",
      "isbn": "",
      "note": "",
      "entry_type": "inproceedings",
      "alpha_key": "CD98"
    },
    {
      "key": "[CFS17]",
      "raw_text": "A. Chiesa, M. A. Forbes, and N. Spooner. A Zero Knowledge Sumcheck and its Applications. Cryptology ePrint Archive, Report 2017/305. 2017.",
      "authors": [
        "Chiesa, A.",
        "Forbes, M. A.",
        "Spooner, N."
      ],
      "title": "A Zero Knowledge Sumcheck and its Applications",
      "year": "2017",
      "venue": "Cryptology ePrint Archive",
      "volume": "",
      "pages": "",
      "doi": "",
      "urls": [],
      "eprint_id": "2017/305",
      "arxiv_id": "",
      "isbn": "",
      "note": "Report 2017/305",
      "entry_type": "techreport",
      "alpha_key": "CFS17"
    },
    {
      "key": "[Che10]",
      "raw_text": "J. H. Cheon. Discrete Logarithm Problems with Auxiliary Inputs. In: Journal of Cryptology 23.3 (2010), pp. 457-476.",
      "authors": [
        "Cheon, J. H."
      ],
      "title": "Discrete Logarithm Problems with Auxiliary Inputs",
      "year": "2010",
      "venue": "Journal of Cryptology",
      "volume": "23(3)",
      "pages": "457-476",
      "doi": "",
      "urls": [],
      "eprint_id": "",
      "arxiv_id": "",
      "isbn": "",
      "note": "",
      "entry_type": "article",
      "alpha_key": "Che10"
    },
    {
      "key": "[COS20]",
      "raw_text": "A. Chiesa, D. Ojha, and N. Spooner. Fractal: Post-Quantum and Transparent Recursive Proofs from Holography. In: EUROCRYPT '20. 2020.",
      "authors": [
        "Chiesa, A.",
        "Ojha, D.",
        "Spooner, N."
      ],
      "title": "Fractal: Post-Quantum and Transparent Recursive Proofs from Holography",
      "year": "2020",
      "venue": "EUROCRYPT 2020",
      "volume": "",
      "pages": "",
      "doi": "",
      "urls": [],
      "eprint_id": "",
      "arxiv_id": "",
      "isbn": "",
      "note": "",
      "entry_type": "inproceedings",
      "alpha_key": "COS20"
    },
    {
      "key": "[Dan+14]",
      "raw_text": "G. Danezis, C. Fournet, J. Groth, and M. Kohlweiss. Square Span Programs with Applications to Succinct NIZK Arguments. In: ASIACRYPT '14. 2014, pp. 532-550.",
      "authors": [
        "Danezis, G.",
        "Fournet, C.",
        "Groth, J.",
        "Kohlweiss, M."
      ],
      "title": "Square Span Programs with Applications to Succinct NIZK Arguments",
      "year": "2014",
      "venue": "ASIACRYPT 2014",
      "volume": "",
      "pages": "532-550",
      "doi": "",
      "urls": [],
      "eprint_id": "",
      "arxiv_id": "",
      "isbn": "",
      "note": "",
      "entry_type": "inproceedings",
      "alpha_key": "DFGK14"
    },
    {
      "key": "[Den02]",
      "raw_text": "A. W. Dent. Adapting the Weaknesses of the Random Oracle Model to the Generic Group Model. In: ASIACRYPT '02. 2002, pp. 100-109.",
      "authors": [
        "Dent, A. W."
      ],
      "title": "Adapting the Weaknesses of the Random Oracle Model to the Generic Group Model",
      "year": "2002",
      "venue": "ASIACRYPT 2002",
      "volume": "",
      "pages": "100-109",
      "doi": "",
      "urls": [],
      "eprint_id": "",
      "arxiv_id": "",
      "isbn": "",
      "note": "",
      "entry_type": "inproceedings",
      "alpha_key": "Den02"
    },
    {
      "key": "[FKL18]",
      "raw_text": "G. Fuchsbauer, E. Kiltz, and J. Loss. The Algebraic Group Model and its Applications. In: CRYPTO '18. 2018, pp. 33-62.",
      "authors": [
        "Fuchsbauer, G.",
        "Kiltz, E.",
        "Loss, J."
      ],
      "title": "The Algebraic Group Model and its Applications",
      "year": "2018",
      "venue": "CRYPTO 2018",
      "volume": "",
      "pages": "33-62",
      "doi": "",
      "urls": [],
      "eprint_id": "",
      "arxiv_id": "",
      "isbn": "",
      "note": "",
      "entry_type": "inproceedings",
      "alpha_key": "FKL18"
    },
    {
      "key": "[FS86]",
      "raw_text": "A. Fiat and A. Shamir. How to prove yourself: practical solutions to identification and signature problems. In: CRYPTO '86. 1986, pp. 186-194.",
      "authors": [
        "Fiat, A.",
        "Shamir, A."
      ],
      "title": "How to prove yourself: practical solutions to identification and signature problems",
      "year": "1986",
      "venue": "CRYPTO 1986",
      "volume": "",
      "pages": "186-194",
      "doi": "",
      "urls": [],
      "eprint_id": "",
      "arxiv_id": "",
      "isbn": "",
      "note": "",
      "entry_type": "inproceedings",
      "alpha_key": "FS86"
    },
    {
      "key": "[Gab19]",
      "raw_text": "A. Gabizon. Improved prover efficiency and SRS size in a Sonic-like system. Cryptology ePrint Archive, Report 2019/601. 2019.",
      "authors": [
        "Gabizon, A."
      ],
      "title": "Improved prover efficiency and SRS size in a Sonic-like system",
      "year": "2019",
      "venue": "Cryptology ePrint Archive",
      "volume": "",
      "pages": "",
      "doi": "",
      "urls": [],
      "eprint_id": "2019/601",
      "arxiv_id": "",
      "isbn": "",
      "note": "Report 2019/601",
      "entry_type": "techreport",
      "alpha_key": "Gab19"
    },
    {
      "key": "[Gen+13]",
      "raw_text": "R. Gennaro, C. Gentry, B. Parno, and M. Raykova. Quadratic Span Programs and Succinct NIZKs without PCPs. In: EUROCRYPT '13. 2013, pp. 626-645.",
      "authors": [
        "Gennaro, R.",
        "Gentry, C.",
        "Parno, B.",
        "Raykova, M."
      ],
      "title": "Quadratic Span Programs and Succinct NIZKs without PCPs",
      "year": "2013",
      "venue": "EUROCRYPT 2013",
      "volume": "",
      "pages": "626-645",
      "doi": "",
      "urls": [],
      "eprint_id": "",
      "arxiv_id": "",
      "isbn": "",
      "note": "",
      "entry_type": "inproceedings",
      "alpha_key": "GGPR13"
    },
    {
      "key": "[GKR15]",
      "raw_text": "S. Goldwasser, Y. T. Kalai, and G. N. Rothblum. Delegating Computation: Interactive Proofs for Muggles. In: Journal of the ACM 62.4 (2015), 27:1-27:64.",
      "authors": [
        "Goldwasser, S.",
        "Kalai, Y. T.",
        "Rothblum, G. N."
      ],
      "title": "Delegating Computation: Interactive Proofs for Muggles",
      "year": "2015",
      "venue": "Journal of the ACM",
      "volume": "62(4)",
      "pages": "27:1-27:64",
      "doi": "",
      "urls": [],
      "eprint_id": "",
      "arxiv_id": "",
      "isbn": "",
      "note": "",
      "entry_type": "article",
      "alpha_key": "GKR15"
    },
    {
      "key": "[GMR89]",
      "raw_text": "S. Goldwasser, S. Micali, and C. Rackoff. The knowledge complexity of interactive proof systems. In: SIAM Journal on Computing 18.1 (1989), pp. 186-208.",
      "authors": [
        "Goldwasser, S.",
        "Micali, S.",
        "Rackoff, C."
      ],
      "title": "The knowledge complexity of interactive proof systems",
      "year": "1989",
      "venue": "SIAM Journal on Computing",
      "volume": "18(1)",
      "pages": "186-208",
      "doi": "",
      "urls": [],
      "eprint_id": "",
      "arxiv_id": "",
      "isbn": "",
      "note": "Preliminary version in STOC 1985",
      "entry_type": "article",
      "alpha_key": "GMR89"
    },
    {
      "key": "[Gro10]",
      "raw_text": "J. Groth. Short Pairing-Based Non-interactive Zero-Knowledge Arguments. In: ASIACRYPT '10. 2010, pp. 321-340.",
      "authors": [
        "Groth, J."
      ],
      "title": "Short Pairing-Based Non-interactive Zero-Knowledge Arguments",
      "year": "2010",
      "venue": "ASIACRYPT 2010",
      "volume": "",
      "pages": "321-340",
      "doi": "",
      "urls": [],
      "eprint_id": "",
      "arxiv_id": "",
      "isbn": "",
      "note": "",
      "entry_type": "inproceedings",
      "alpha_key": "Gro10"
    },
    {
      "key": "[Gro16]",
      "raw_text": "J. Groth. On the Size of Pairing-Based Non-interactive Arguments. In: EUROCRYPT '16. 2016, pp. 305-326.",
      "authors": [
        "Groth, J."
      ],
      "title": "On the Size of Pairing-Based Non-interactive Arguments",
      "year": "2016",
      "venue": "EUROCRYPT 2016",
      "volume": "",
      "pages": "305-326",
      "doi": "",
      "urls": [],
      "eprint_id": "",
      "arxiv_id": "",
      "isbn": "",
      "note": "",
      "entry_type": "inproceedings",
      "alpha_key": "Gro16"
    },
    {
      "key": "[Gro+18]",
      "raw_text": "J. Groth, M. Kohlweiss, M. Maller, S. Meiklejohn, and I. Miers. Updatable and Universal Common Reference Strings with Applications to zk-SNARKs. In: CRYPTO '18. 2018, pp. 698-728.",
      "authors": [
        "Groth, J.",
        "Kohlweiss, M.",
        "Maller, M.",
        "Meiklejohn, S.",
        "Miers, I."
      ],
      "title": "Updatable and Universal Common Reference Strings with Applications to zk-SNARKs",
      "year": "2018",
      "venue": "CRYPTO 2018",
      "volume": "",
      "pages": "698-728",
      "doi": "",
      "urls": [],
      "eprint_id": "",
      "arxiv_id": "",
      "isbn": "",
      "note": "",
      "entry_type": "inproceedings",
      "alpha_key": "GKM+18"
    },
    {
      "key": "[GWC19]",
      "raw_text": "A. Gabizon, Z. J. Williamson, and O. Ciobotaru. PLONK: Permutations over Lagrange-bases for Oecumenical Noninteractive arguments of Knowledge. Cryptology ePrint Archive, Report 2019/953. 2019.",
      "authors": [
        "Gabizon, A.",
        "Williamson, Z. J.",
        "Ciobotaru, O."
      ],
      "title": "PLONK: Permutations over Lagrange-bases for Oecumenical Noninteractive arguments of Knowledge",
      "year": "2019",
      "venue": "Cryptology ePrint Archive",
      "volume": "",
      "pages": "",
      "doi": "",
      "urls": [],
      "eprint_id": "2019/953",
      "arxiv_id": "",
      "isbn": "",
      "note": "Report 2019/953",
      "entry_type": "techreport",
      "alpha_key": "GWC19"
    },
    {
      "key": "[Kil92]",
      "raw_text": "J. Kilian. A note on efficient zero-knowledge proofs and arguments. In: STOC '92. 1992, pp. 723-732.",
      "authors": [
        "Kilian, J."
      ],
      "title": "A note on efficient zero-knowledge proofs and arguments",
      "year": "1992",
      "venue": "STOC 1992",
      "volume": "",
      "pages": "723-732",
      "doi": "",
      "urls": [],
      "eprint_id": "",
      "arxiv_id": "",
      "isbn": "",
      "note": "",
      "entry_type": "inproceedings",
      "alpha_key": "Kil92"
    },
    {
      "key": "[KKM07]",
      "raw_text": "S. Kozaki, T. Kutsuma, and K. Matsuo. Remarks on Cheon's Algorithms for Pairing-Related Problems. In: Pairing '07. 2007, pp. 302-316.",
      "authors": [
        "Kozaki, S.",
        "Kutsuma, T.",
        "Matsuo, K."
      ],
      "title": "Remarks on Cheon's Algorithms for Pairing-Related Problems",
      "year": "2007",
      "venue": "Pairing 2007",
      "volume": "",
      "pages": "302-316",
      "doi": "",
      "urls": [],
      "eprint_id": "",
      "arxiv_id": "",
      "isbn": "",
      "note": "",
      "entry_type": "inproceedings",
      "alpha_key": "KKM07"
    },
    {
      "key": "[KZG10]",
      "raw_text": "A. Kate, G. M. Zaverucha, and I. Goldberg. Constant-Size Commitments to Polynomials and Their Applications. In: ASIACRYPT '10. 2010, pp. 177-194.",
      "authors": [
        "Kate, A.",
        "Zaverucha, G. M.",
        "Goldberg, I."
      ],
      "title": "Constant-Size Commitments to Polynomials and Their Applications",
      "year": "2010",
      "venue": "ASIACRYPT 2010",
      "volume": "",
      "pages": "177-194",
      "doi": "",
      "urls": [],
      "eprint_id": "",
      "arxiv_id": "",
      "isbn": "",
      "note": "",
      "entry_type": "inproceedings",
      "alpha_key": "KZG10"
    },
    {
      "key": "[Lip12]",
      "raw_text": "H. Lipmaa. Progression-Free Sets and Sublinear Pairing-Based Non-Interactive Zero-Knowledge Arguments. In: TCC '12. 2012, pp. 169-189.",
      "authors": [
        "Lipmaa, H."
      ],
      "title": "Progression-Free Sets and Sublinear Pairing-Based Non-Interactive Zero-Knowledge Arguments",
      "year": "2012",
      "venue": "TCC 2012",
      "volume": "",
      "pages": "169-189",
      "doi": "",
      "urls": [],
      "eprint_id": "",
      "arxiv_id": "",
      "isbn": "",
      "note": "",
      "entry_type": "inproceedings",
      "alpha_key": "Lip12"
    },
    {
      "key": "[Mal+19]",
      "raw_text": "M. Maller, S. Bowe, M. Kohlweiss, and S. Meiklejohn. Sonic: Zero-Knowledge SNARKs from Linear-Size Universal and Updateable Structured Reference Strings. In: CCS '19. 2019, pp. 2111-2128.",
      "authors": [
        "Maller, M.",
        "Bowe, S.",
        "Kohlweiss, M.",
        "Meiklejohn, S."
      ],
      "title": "Sonic: Zero-Knowledge SNARKs from Linear-Size Universal and Updateable Structured Reference Strings",
      "year": "2019",
      "venue": "ACM CCS 2019",
      "volume": "",
      "pages": "2111-2128",
      "doi": "",
      "urls": [],
      "eprint_id": "",
      "arxiv_id": "",
      "isbn": "",
      "note": "",
      "entry_type": "inproceedings",
      "alpha_key": "MBKM19"
    },
    {
      "key": "[Mau05]",
      "raw_text": "U. M. Maurer. Abstract Models of Computation in Cryptography. In: IMA '05. 2005, pp. 1-12.",
      "authors": [
        "Maurer, U. M."
      ],
      "title": "Abstract Models of Computation in Cryptography",
      "year": "2005",
      "venue": "IMA 2005",
      "volume": "",
      "pages": "1-12",
      "doi": "",
      "urls": [],
      "eprint_id": "",
      "arxiv_id": "",
      "isbn": "",
      "note": "",
      "entry_type": "inproceedings",
      "alpha_key": "Mau05"
    },
    {
      "key": "[PST13]",
      "raw_text": "C. Papamanthou, E. Shi, and R. Tamassia. Signatures of Correct Computation. In: TCC '13. 2013, pp. 222-242.",
      "authors": [
        "Papamanthou, C.",
        "Shi, E.",
        "Tamassia, R."
      ],
      "title": "Signatures of Correct Computation",
      "year": "2013",
      "venue": "TCC 2013",
      "volume": "",
      "pages": "222-242",
      "doi": "",
      "urls": [],
      "eprint_id": "",
      "arxiv_id": "",
      "isbn": "",
      "note": "",
      "entry_type": "inproceedings",
      "alpha_key": "PST13"
    },
    {
      "key": "[PV05]",
      "raw_text": "P. Paillier and D. Vergnaud. Discrete-Log-Based Signatures May Not Be Equivalent to Discrete Log. In: ASIACRYPT '05. 2005, pp. 1-20.",
      "authors": [
        "Paillier, P.",
        "Vergnaud, D."
      ],
      "title": "Discrete-Log-Based Signatures May Not Be Equivalent to Discrete Log",
      "year": "2005",
      "venue": "ASIACRYPT 2005",
      "volume": "",
      "pages": "1-20",
      "doi": "",
      "urls": [],
      "eprint_id": "",
      "arxiv_id": "",
      "isbn": "",
      "note": "",
      "entry_type": "inproceedings",
      "alpha_key": "PV05"
    },
    {
      "key": "[RRR16]",
      "raw_text": "O. Reingold, R. Rothblum, and G. Rothblum. Constant-Round Interactive Proofs for Delegating Computation. In: STOC '16. 2016, pp. 49-62.",
      "authors": [
        "Reingold, O.",
        "Rothblum, R.",
        "Rothblum, G."
      ],
      "title": "Constant-Round Interactive Proofs for Delegating Computation",
      "year": "2016",
      "venue": "STOC 2016",
      "volume": "",
      "pages": "49-62",
      "doi": "",
      "urls": [],
      "eprint_id": "",
      "arxiv_id": "",
      "isbn": "",
      "note": "",
      "entry_type": "inproceedings",
      "alpha_key": "RRR16"
    },
    {
      "key": "[Set19]",
      "raw_text": "S. Setty. Spartan: Efficient and general-purpose zkSNARKs without trusted setup. Cryptology ePrint Archive, Report 2019/550. 2019.",
      "authors": [
        "Setty, S."
      ],
      "title": "Spartan: Efficient and general-purpose zkSNARKs without trusted setup",
      "year": "2019",
      "venue": "Cryptology ePrint Archive",
      "volume": "",
      "pages": "",
      "doi": "",
      "urls": [],
      "eprint_id": "2019/550",
      "arxiv_id": "",
      "isbn": "",
      "note": "Report 2019/550",
      "entry_type": "techreport",
      "alpha_key": "Set19"
    },
    {
      "key": "[Sho97]",
      "raw_text": "V. Shoup. Lower bounds for discrete logarithms and related problems. In: EUROCRYPT '97. 1997, pp. 256-266.",
      "authors": [
        "Shoup, V."
      ],
      "title": "Lower bounds for discrete logarithms and related problems",
      "year": "1997",
      "venue": "EUROCRYPT 1997",
      "volume": "",
      "pages": "256-266",
      "doi": "",
      "urls": [],
      "eprint_id": "",
      "arxiv_id": "",
      "isbn": "",
      "note": "",
      "entry_type": "inproceedings",
      "alpha_key": "Sho97"
    },
    {
      "key": "[Wah+18]",
      "raw_text": "R. S. Wahby, I. Tzialla, A. Shelat, J. Thaler, and M. Walfish. Doubly-Efficient zkSNARKs Without Trusted Setup. In: S&P '18. 2018, pp. 926-943.",
      "authors": [
        "Wahby, R. S.",
        "Tzialla, I.",
        "Shelat, A.",
        "Thaler, J.",
        "Walfish, M."
      ],
      "title": "Doubly-Efficient zkSNARKs Without Trusted Setup",
      "year": "2018",
      "venue": "IEEE S&P 2018",
      "volume": "",
      "pages": "926-943",
      "doi": "",
      "urls": [],
      "eprint_id": "",
      "arxiv_id": "",
      "isbn": "",
      "note": "",
      "entry_type": "inproceedings",
      "alpha_key": "WTS+18"
    },
    {
      "key": "[Xie+19]",
      "raw_text": "T. Xie, J. Zhang, Y. Zhang, C. Papamanthou, and D. Song. Libra: Succinct Zero-Knowledge Proofs with Optimal Prover Computation. In: CRYPTO '19. 2019, pp. 733-764.",
      "authors": [
        "Xie, T.",
        "Zhang, J.",
        "Zhang, Y.",
        "Papamanthou, C.",
        "Song, D."
      ],
      "title": "Libra: Succinct Zero-Knowledge Proofs with Optimal Prover Computation",
      "year": "2019",
      "venue": "CRYPTO 2019",
      "volume": "",
      "pages": "733-764",
      "doi": "",
      "urls": [],
      "eprint_id": "",
      "arxiv_id": "",
      "isbn": "",
      "note": "",
      "entry_type": "inproceedings",
      "alpha_key": "XZZ+19"
    },
    {
      "key": "[Zcash]",
      "raw_text": "Zcash. https://z.cash/. 2014.",
      "authors": [],
      "title": "Zcash",
      "year": "2014",
      "venue": "",
      "volume": "",
      "pages": "",
      "doi": "",
      "urls": [
        "https://z.cash/"
      ],
      "eprint_id": "",
      "arxiv_id": "",
      "isbn": "",
      "note": "",
      "entry_type": "misc",
      "alpha_key": ""
    },
    {
      "key": "[ZcashMPC]",
      "raw_text": "The Zcash Ceremony. https://z.cash/blog/the-design-of-the-ceremony.html. 2016.",
      "authors": [],
      "title": "The Zcash Ceremony",
      "year": "2016",
      "venue": "",
      "volume": "",
      "pages": "",
      "doi": "",
      "urls": [
        "https://z.cash/blog/the-design-of-the-ceremony.html"
      ],
      "eprint_id": "",
      "arxiv_id": "",
      "isbn": "",
      "note": "",
      "entry_type": "misc",
      "alpha_key": ""
    },
    {
      "key": "[Zha+17a]",
      "raw_text": "Y. Zhang, D. Genkin, J. Katz, D. Papadopoulos, and C. Papamanthou. A Zero-Knowledge Version of vSQL. Cryptology ePrint Archive, Report 2017/1146. 2017.",
      "authors": [
        "Zhang, Y.",
        "Genkin, D.",
        "Katz, J.",
        "Papadopoulos, D.",
        "Papamanthou, C."
      ],
      "title": "A Zero-Knowledge Version of vSQL",
      "year": "2017",
      "venue": "Cryptology ePrint Archive",
      "volume": "",
      "pages": "",
      "doi": "",
      "urls": [],
      "eprint_id": "2017/1146",
      "arxiv_id": "",
      "isbn": "",
      "note": "Report 2017/1146",
      "entry_type": "techreport",
      "alpha_key": "ZGK+17"
    },
    {
      "key": "[Zha+17b]",
      "raw_text": "Y. Zhang, D. Genkin, J. Katz, D. Papadopoulos, and C. Papamanthou. vSQL: Verifying Arbitrary SQL Queries over Dynamic Outsourced Databases. In: S&P '17. 2017, pp. 863-880.",
      "authors": [
        "Zhang, Y.",
        "Genkin, D.",
        "Katz, J.",
        "Papadopoulos, D.",
        "Papamanthou, C."
      ],
      "title": "vSQL: Verifying Arbitrary SQL Queries over Dynamic Outsourced Databases",
      "year": "2017",
      "venue": "IEEE S&P 2017",
      "volume": "",
      "pages": "863-880",
      "doi": "",
      "urls": [],
      "eprint_id": "",
      "arxiv_id": "",
      "isbn": "",
      "note": "",
      "entry_type": "inproceedings",
      "alpha_key": "ZGK+17"
    },
    {
      "key": "[Zha+18]",
      "raw_text": "Y. Zhang, D. Genkin, J. Katz, D. Papadopoulos, and C. Papamanthou. vRAM: Faster Verifiable RAM with Program-Independent Preprocessing. In: S&P '18. 2018, pp. 908-925.",
      "authors": [
        "Zhang, Y.",
        "Genkin, D.",
        "Katz, J.",
        "Papadopoulos, D.",
        "Papamanthou, C."
      ],
      "title": "vRAM: Faster Verifiable RAM with Program-Independent Preprocessing",
      "year": "2018",
      "venue": "IEEE S&P 2018",
      "volume": "",
      "pages": "908-925",
      "doi": "",
      "urls": [],
      "eprint_id": "",
      "arxiv_id": "",
      "isbn": "",
      "note": "",
      "entry_type": "inproceedings",
      "alpha_key": "ZGK+18"
    }
  ]
}
