{
  "backend": "modal-marker",
  "converted_at": "2026-03-16T19:28:44.116092+00:00",
  "elapsed_seconds": 45.22,
  "pdf_sha256": "9a10cf9bef2ceeef4456833a7c5ab12fac73a7f727d2fdd5574a48f5179a944a",
  "source_pdf": "2020_643.pdf",
  "output_path": "2020_643/2020_643.md",
  "backend_version": "",
  "machine": {
    "hostname": "modal",
    "os": "Linux",
    "os_version": "4.4.0",
    "arch": "x86_64",
    "python_version": "3.12.10",
    "cpu_count": 17,
    "provider": "modal",
    "gpu_count": 1,
    "gpu_name": "NVIDIA A100-SXM4-40GB",
    "gpu_vram_mb": 40441,
    "cuda_version": "12.8"
  },
  "estimated_cost_usd": 0.013838
}
