{
  "backend": "modal-marker",
  "converted_at": "2026-03-16T13:07:43.447065+00:00",
  "elapsed_seconds": 86.57,
  "pdf_sha256": "f07f1238cc99b186eee01f3aa4e1aabbdbe9e49884a899629e6b5905ad680103",
  "source_pdf": "2020_522.pdf",
  "output_path": "2020_522/2020_522.md",
  "backend_version": "",
  "machine": {
    "hostname": "modal",
    "os": "Linux",
    "os_version": "4.4.0",
    "arch": "x86_64",
    "python_version": "3.12.10",
    "cpu_count": 17,
    "provider": "modal",
    "gpu_count": 1,
    "gpu_name": "NVIDIA A100-SXM4-40GB",
    "gpu_vram_mb": 40441,
    "cuda_version": "12.8"
  },
  "estimated_cost_usd": 0.026491
}
