{
  "backend": "modal-marker",
  "converted_at": "2026-04-01T22:06:53.806929+00:00",
  "elapsed_seconds": 30.38,
  "pdf_sha256": "b166a86fcee6a06aeb775573f91851f56fb0d5818afbdc1d8c031cf1dc96abc3",
  "source_pdf": "2013_322.pdf",
  "output_path": "2013_322/2013_322.md",
  "backend_version": "",
  "machine": {
    "hostname": "modal",
    "os": "Linux",
    "os_version": "4.4.0",
    "arch": "x86_64",
    "python_version": "3.12.10",
    "cpu_count": 17,
    "provider": "modal",
    "gpu_count": 1,
    "gpu_name": "NVIDIA A100-SXM4-40GB",
    "gpu_vram_mb": 40441,
    "cuda_version": "12.8"
  },
  "estimated_cost_usd": 0.009296
}
