{
  "paper_id": "2013_641",
  "references": [
    {
      "key": "[AIR01]",
      "raw_text": "William Aiello, Yuval Ishai, and Omer Reingold. Priced oblivious transfer: How to sell digital goods. In *EUROCRYPT*, pages 119\u2013135, 2001.",
      "authors": [
        "Aiello, William",
        "Ishai, Yuval",
        "Reingold, Omer"
      ],
      "title": "Priced oblivious transfer: How to sell digital goods",
      "year": "2001",
      "venue": "EUROCRYPT",
      "volume": "",
      "pages": "119\u2013135",
      "doi": "",
      "urls": [],
      "eprint_id": "",
      "arxiv_id": "",
      "isbn": "",
      "note": "",
      "entry_type": "inproceedings",
      "alpha_key": "AIR01"
    },
    {
      "key": "[Bar01]",
      "raw_text": "Boaz Barak. How to go beyond the black-box simulation barrier. In *FOCS*, pages 106\u2013115, 2001.",
      "authors": [
        "Barak, Boaz"
      ],
      "title": "How to go beyond the black-box simulation barrier",
      "year": "2001",
      "venue": "FOCS",
      "volume": "",
      "pages": "106\u2013115",
      "doi": "",
      "urls": [],
      "eprint_id": "",
      "arxiv_id": "",
      "isbn": "",
      "note": "",
      "entry_type": "inproceedings",
      "alpha_key": "Bar01"
    },
    {
      "key": "[BC12]",
      "raw_text": "Nir Bitansky and Alessandro Chiesa. Succinct arguments from multi-prover interactive proofs and their efficiency benefits. In *CRYPTO*, pages 255\u2013272, 2012.",
      "authors": [
        "Bitansky, Nir",
        "Chiesa, Alessandro"
      ],
      "title": "Succinct arguments from multi-prover interactive proofs and their efficiency benefits",
      "year": "2012",
      "venue": "CRYPTO",
      "volume": "",
      "pages": "255\u2013272",
      "doi": "",
      "urls": [],
      "eprint_id": "",
      "arxiv_id": "",
      "isbn": "",
      "note": "",
      "entry_type": "inproceedings",
      "alpha_key": "BC12"
    },
    {
      "key": "[BCCT12]",
      "raw_text": "Nir Bitansky, Ran Canetti, Alessandro Chiesa, and Eran Tromer. From extractable collision resistance to succinct non-interactive arguments of knowledge, and back again. In *Proceedings of the 3rd Innovations in Theoretical Computer Science Conference*, ITCS '12, pages 326\u2013349, 2012.",
      "authors": [
        "Bitansky, Nir",
        "Canetti, Ran",
        "Chiesa, Alessandro",
        "Tromer, Eran"
      ],
      "title": "From extractable collision resistance to succinct non-interactive arguments of knowledge, and back again",
      "year": "2012",
      "venue": "Proceedings of the 3rd Innovations in Theoretical Computer Science Conference",
      "volume": "",
      "pages": "326\u2013349",
      "doi": "",
      "urls": [],
      "eprint_id": "",
      "arxiv_id": "",
      "isbn": "",
      "note": "",
      "entry_type": "inproceedings",
      "alpha_key": "BCCT12"
    },
    {
      "key": "[BCCT13]",
      "raw_text": "Nir Bitansky, Ran Canetti, Alessandro Chiesa, and Eran Tromer. Recursive composition and bootstrapping for snarks and proof-carrying data. In *STOC*, pages 111\u2013120, 2013.",
      "authors": [
        "Bitansky, Nir",
        "Canetti, Ran",
        "Chiesa, Alessandro",
        "Tromer, Eran"
      ],
      "title": "Recursive composition and bootstrapping for snarks and proof-carrying data",
      "year": "2013",
      "venue": "STOC",
      "volume": "",
      "pages": "111\u2013120",
      "doi": "",
      "urls": [],
      "eprint_id": "",
      "arxiv_id": "",
      "isbn": "",
      "note": "",
      "entry_type": "inproceedings",
      "alpha_key": "BCCT13"
    },
    {
      "key": "[BCPR13]",
      "raw_text": "Nir Bitansky, Ran Canetti, Omer Paneth, and Alon Rosen. Indistinguishability obfuscation vs. auxiliary-input extractable functions: One must fall. *IACR Cryptology ePrint Archive*, 2013:641, 2013.",
      "authors": [
        "Bitansky, Nir",
        "Canetti, Ran",
        "Paneth, Omer",
        "Rosen, Alon"
      ],
      "title": "Indistinguishability obfuscation vs. auxiliary-input extractable functions: One must fall",
      "year": "2013",
      "venue": "IACR Cryptology ePrint Archive",
      "volume": "",
      "pages": "",
      "doi": "",
      "urls": [
        "https://eprint.iacr.org/2013/641"
      ],
      "eprint_id": "2013/641",
      "arxiv_id": "",
      "isbn": "",
      "note": "",
      "entry_type": "article",
      "alpha_key": "BCPR13"
    },
    {
      "key": "[BCPR14]",
      "raw_text": "Nir Bitansky, Ran Canetti, Omer Paneth, and Alon Rosen. On the existence of extractable one-way functions. In *Proceedings of the 46th Annual ACM Symposium on Theory of Computing*, STOC '14, 2014.",
      "authors": [
        "Bitansky, Nir",
        "Canetti, Ran",
        "Paneth, Omer",
        "Rosen, Alon"
      ],
      "title": "On the existence of extractable one-way functions",
      "year": "2014",
      "venue": "Proceedings of the 46th Annual ACM Symposium on Theory of Computing",
      "volume": "",
      "pages": "",
      "doi": "",
      "urls": [],
      "eprint_id": "",
      "arxiv_id": "",
      "isbn": "",
      "note": "",
      "entry_type": "inproceedings",
      "alpha_key": "BCPR14"
    },
    {
      "key": "[BG08]",
      "raw_text": "Boaz Barak and Oded Goldreich. Universal arguments and their applications. *SIAM J. Comput.*, 38(5):1661\u20131694, 2008.",
      "authors": [
        "Barak, Boaz",
        "Goldreich, Oded"
      ],
      "title": "Universal arguments and their applications",
      "year": "2008",
      "venue": "SIAM J. Comput.",
      "volume": "38",
      "pages": "1661\u20131694",
      "doi": "",
      "urls": [],
      "eprint_id": "",
      "arxiv_id": "",
      "isbn": "",
      "note": "",
      "entry_type": "article",
      "alpha_key": "BG08"
    },
    {
      "key": "[Blu86]",
      "raw_text": "Manuel Blum. How to prove a theorem so no one else can claim it. In *Proceedings of the International Congress of Mathematicians*, pages 1444\u20131451, 1986.",
      "authors": [
        "Blum, Manuel"
      ],
      "title": "How to prove a theorem so no one else can claim it",
      "year": "1986",
      "venue": "Proceedings of the International Congress of Mathematicians",
      "volume": "",
      "pages": "1444\u20131451",
      "doi": "",
      "urls": [],
      "eprint_id": "",
      "arxiv_id": "",
      "isbn": "",
      "note": "",
      "entry_type": "inproceedings",
      "alpha_key": "Blu86"
    },
    {
      "key": "[BLV06]",
      "raw_text": "Boaz Barak, Yehuda Lindell, and Salil P. Vadhan. Lower bounds for non-black-box zero knowledge. *J. Comput. Syst. Sci.*, 72(2):321\u2013391, 2006.",
      "authors": [
        "Barak, Boaz",
        "Lindell, Yehuda",
        "Vadhan, Salil P."
      ],
      "title": "Lower bounds for non-black-box zero knowledge",
      "year": "2006",
      "venue": "J. Comput. Syst. Sci.",
      "volume": "72",
      "pages": "321\u2013391",
      "doi": "",
      "urls": [],
      "eprint_id": "",
      "arxiv_id": "",
      "isbn": "",
      "note": "",
      "entry_type": "article",
      "alpha_key": "BLV06"
    },
    {
      "key": "[BM84]",
      "raw_text": "Manuel Blum and Silvio Micali. How to generate cryptographically strong sequences of pseudo-random bits. *SIAM J. Comput.*, 13(4):850\u2013864, 1984.",
      "authors": [
        "Blum, Manuel",
        "Micali, Silvio"
      ],
      "title": "How to generate cryptographically strong sequences of pseudo-random bits",
      "year": "1984",
      "venue": "SIAM J. Comput.",
      "volume": "13",
      "pages": "850\u2013864",
      "doi": "",
      "urls": [],
      "eprint_id": "",
      "arxiv_id": "",
      "isbn": "",
      "note": "",
      "entry_type": "article",
      "alpha_key": "BM84"
    },
    {
      "key": "[BP04]",
      "raw_text": "Mihir Bellare and Adriana Palacio. The knowledge-of-exponent assumptions and 3-round zero-knowledge protocols. In *Proceedings of the 24th Annual International Cryptology Conference*, pages 273\u2013289, 2004.",
      "authors": [
        "Bellare, Mihir",
        "Palacio, Adriana"
      ],
      "title": "The knowledge-of-exponent assumptions and 3-round zero-knowledge protocols",
      "year": "2004",
      "venue": "Proceedings of the 24th Annual International Cryptology Conference",
      "volume": "",
      "pages": "273\u2013289",
      "doi": "",
      "urls": [],
      "eprint_id": "",
      "arxiv_id": "",
      "isbn": "",
      "note": "",
      "entry_type": "inproceedings",
      "alpha_key": "BP04"
    },
    {
      "key": "[BP13]",
      "raw_text": "Nir Bitansky and Omer Paneth. On the impossibility of approximate obfuscation and applications to resettable cryptography. In *STOC*, pages 241\u2013250, 2013.",
      "authors": [
        "Bitansky, Nir",
        "Paneth, Omer"
      ],
      "title": "On the impossibility of approximate obfuscation and applications to resettable cryptography",
      "year": "2013",
      "venue": "STOC",
      "volume": "",
      "pages": "241\u2013250",
      "doi": "",
      "urls": [],
      "eprint_id": "",
      "arxiv_id": "",
      "isbn": "",
      "note": "",
      "entry_type": "inproceedings",
      "alpha_key": "BP13"
    },
    {
      "key": "[BV11]",
      "raw_text": "Zvika Brakerski and Vinod Vaikuntanathan. Efficient fully homomorphic encryption from (standard) lwe. In *FOCS*, pages 97\u2013106, 2011.",
      "authors": [
        "Brakerski, Zvika",
        "Vaikuntanathan, Vinod"
      ],
      "title": "Efficient fully homomorphic encryption from (standard) lwe",
      "year": "2011",
      "venue": "FOCS",
      "volume": "",
      "pages": "97\u2013106",
      "doi": "",
      "urls": [],
      "eprint_id": "",
      "arxiv_id": "",
      "isbn": "",
      "note": "",
      "entry_type": "inproceedings",
      "alpha_key": "BV11"
    },
    {
      "key": "[Can00]",
      "raw_text": "Ran Canetti. Security and composition of multiparty cryptographic protocols. *Journal of Cryptology*, pages 143\u2013202, 2000.",
      "authors": [
        "Canetti, Ran"
      ],
      "title": "Security and composition of multiparty cryptographic protocols",
      "year": "2000",
      "venue": "Journal of Cryptology",
      "volume": "",
      "pages": "143\u2013202",
      "doi": "",
      "urls": [],
      "eprint_id": "",
      "arxiv_id": "",
      "isbn": "",
      "note": "",
      "entry_type": "article",
      "alpha_key": "Can00"
    },
    {
      "key": "[Can01]",
      "raw_text": "Ran Canetti. Universally composable security: A new paradigm for cryptographic protocols. In *Proceedings of the 42nd Annual IEEE Symposium on Foundations of Computer Science*, pages 136\u2013145, 2001.",
      "authors": [
        "Canetti, Ran"
      ],
      "title": "Universally composable security: A new paradigm for cryptographic protocols",
      "year": "2001",
      "venue": "Proceedings of the 42nd Annual IEEE Symposium on Foundations of Computer Science",
      "volume": "",
      "pages": "136\u2013145",
      "doi": "",
      "urls": [],
      "eprint_id": "",
      "arxiv_id": "",
      "isbn": "",
      "note": "",
      "entry_type": "inproceedings",
      "alpha_key": "Can01"
    },
    {
      "key": "[CD08]",
      "raw_text": "Ran Canetti and Ronny Ramzi Dakdouk. Extractable perfectly one-way functions. In *Proceedings of the 35th International Colloquium on Automata, Languages and Programming*, pages 449\u2013460, 2008.",
      "authors": [
        "Canetti, Ran",
        "Dakdouk, Ronny Ramzi"
      ],
      "title": "Extractable perfectly one-way functions",
      "year": "2008",
      "venue": "Proceedings of the 35th International Colloquium on Automata, Languages and Programming",
      "volume": "",
      "pages": "449\u2013460",
      "doi": "",
      "urls": [],
      "eprint_id": "",
      "arxiv_id": "",
      "isbn": "",
      "note": "",
      "entry_type": "inproceedings",
      "alpha_key": "CD08"
    },
    {
      "key": "[CD09]",
      "raw_text": "Ran Canetti and Ronny Ramzi Dakdouk. Towards a theory of extractable functions. In *TCC*, pages 595\u2013613, 2009.",
      "authors": [
        "Canetti, Ran",
        "Dakdouk, Ronny Ramzi"
      ],
      "title": "Towards a theory of extractable functions",
      "year": "2009",
      "venue": "TCC",
      "volume": "",
      "pages": "595\u2013613",
      "doi": "",
      "urls": [],
      "eprint_id": "",
      "arxiv_id": "",
      "isbn": "",
      "note": "",
      "entry_type": "inproceedings",
      "alpha_key": "CD09"
    },
    {
      "key": "[CLP13]",
      "raw_text": "Kai-Min Chung, Huijia Lin, and Rafael Pass. Constant-round concurrent zero knowledge from p-certificates. In *FOCS*, 2013.",
      "authors": [
        "Chung, Kai-Min",
        "Lin, Huijia",
        "Pass, Rafael"
      ],
      "title": "Constant-round concurrent zero knowledge from p-certificates",
      "year": "2013",
      "venue": "FOCS",
      "volume": "",
      "pages": "",
      "doi": "",
      "urls": [],
      "eprint_id": "",
      "arxiv_id": "",
      "isbn": "",
      "note": "",
      "entry_type": "inproceedings",
      "alpha_key": "CLP13"
    },
    {
      "key": "[COSV12]",
      "raw_text": "Chongwon Cho, Rafail Ostrovsky, Alessandra Scafuro, and Ivan Visconti. Simultaneously resettable arguments of knowledge. In *TCC*, pages 530\u2013547, 2012.",
      "authors": [
        "Cho, Chongwon",
        "Ostrovsky, Rafail",
        "Scafuro, Alessandra",
        "Visconti, Ivan"
      ],
      "title": "Simultaneously resettable arguments of knowledge",
      "year": "2012",
      "venue": "TCC",
      "volume": "",
      "pages": "530\u2013547",
      "doi": "",
      "urls": [],
      "eprint_id": "",
      "arxiv_id": "",
      "isbn": "",
      "note": "",
      "entry_type": "inproceedings",
      "alpha_key": "COSV12"
    },
    {
      "key": "[Dam92]",
      "raw_text": "Ivan Damgard. Towards practical public key systems secure against chosen ciphertext at- \u02da tacks. In *Proceedings of CRYPTO91*, pages 445\u2013456, 1992.",
      "authors": [
        "Damg\u00e5rd, Ivan"
      ],
      "title": "Towards practical public key systems secure against chosen ciphertext attacks",
      "year": "1992",
      "venue": "Proceedings of CRYPTO91",
      "volume": "",
      "pages": "445\u2013456",
      "doi": "",
      "urls": [],
      "eprint_id": "",
      "arxiv_id": "",
      "isbn": "",
      "note": "",
      "entry_type": "inproceedings",
      "alpha_key": "Dam92"
    },
    {
      "key": "[DN07]",
      "raw_text": "Cynthia Dwork and Moni Naor. Zaps and their applications. *SIAM J. Comput.*, 36(6):1513\u2013 1543, 2007.",
      "authors": [
        "Dwork, Cynthia",
        "Naor, Moni"
      ],
      "title": "Zaps and their applications",
      "year": "2007",
      "venue": "SIAM J. Comput.",
      "volume": "36",
      "pages": "1513\u20131543",
      "doi": "",
      "urls": [],
      "eprint_id": "",
      "arxiv_id": "",
      "isbn": "",
      "note": "",
      "entry_type": "article",
      "alpha_key": "DN07"
    },
    {
      "key": "[FLS99]",
      "raw_text": "Uriel Feige, Dror Lapidot, and Adi Shamir. Multiple noninteractive zero knowledge proofs under general assumptions. *SIAM J. Comput.*, 29(1):1\u201328, 1999.",
      "authors": [
        "Feige, Uriel",
        "Lapidot, Dror",
        "Shamir, Adi"
      ],
      "title": "Multiple noninteractive zero knowledge proofs under general assumptions",
      "year": "1999",
      "venue": "SIAM J. Comput.",
      "volume": "29",
      "pages": "1\u201328",
      "doi": "",
      "urls": [],
      "eprint_id": "",
      "arxiv_id": "",
      "isbn": "",
      "note": "",
      "entry_type": "article",
      "alpha_key": "FLS99"
    },
    {
      "key": "[FS89]",
      "raw_text": "Uriel Feige and Adi Shamir. Zero knowledge proofs of knowledge in two rounds. pages 526\u2013544, 1989.",
      "authors": [
        "Feige, Uriel",
        "Shamir, Adi"
      ],
      "title": "Zero knowledge proofs of knowledge in two rounds",
      "year": "1989",
      "venue": "",
      "volume": "",
      "pages": "526\u2013544",
      "doi": "",
      "urls": [],
      "eprint_id": "",
      "arxiv_id": "",
      "isbn": "",
      "note": "",
      "entry_type": "unknown",
      "alpha_key": "FS89"
    },
    {
      "key": "[FS90]",
      "raw_text": "Uriel Feige and Adi Shamir. Witness indistinguishable and witness hiding protocols. In *STOC*, pages 416\u2013426, 1990.",
      "authors": [
        "Feige, Uriel",
        "Shamir, Adi"
      ],
      "title": "Witness indistinguishable and witness hiding protocols",
      "year": "1990",
      "venue": "STOC",
      "volume": "",
      "pages": "416\u2013426",
      "doi": "",
      "urls": [],
      "eprint_id": "",
      "arxiv_id": "",
      "isbn": "",
      "note": "",
      "entry_type": "inproceedings",
      "alpha_key": "FS90"
    },
    {
      "key": "[GHV10]",
      "raw_text": "Craig Gentry, Shai Halevi, and Vinod Vaikuntanathan. *i*-hop homomorphic encryption and rerandomizable yao circuits. In *CRYPTO*, pages 155\u2013172, 2010.",
      "authors": [
        "Gentry, Craig",
        "Halevi, Shai",
        "Vaikuntanathan, Vinod"
      ],
      "title": "*i*-hop homomorphic encryption and rerandomizable yao circuits",
      "year": "2010",
      "venue": "CRYPTO",
      "volume": "",
      "pages": "155\u2013172",
      "doi": "",
      "urls": [],
      "eprint_id": "",
      "arxiv_id": "",
      "isbn": "",
      "note": "",
      "entry_type": "inproceedings",
      "alpha_key": "GHV10"
    },
    {
      "key": "[GK96]",
      "raw_text": "Oded Goldreich and Hugo Krawczyk. On the composition of zero-knowledge proof systems. *SIAM J. Comput.*, 25(1):169\u2013192, 1996.",
      "authors": [
        "Goldreich, Oded",
        "Krawczyk, Hugo"
      ],
      "title": "On the composition of zero-knowledge proof systems",
      "year": "1996",
      "venue": "SIAM J. Comput.",
      "volume": "25",
      "pages": "169\u2013192",
      "doi": "",
      "urls": [],
      "eprint_id": "",
      "arxiv_id": "",
      "isbn": "",
      "note": "",
      "entry_type": "article",
      "alpha_key": "GK96"
    },
    {
      "key": "[GL89]",
      "raw_text": "O. Goldreich and L. A. Levin. A hard-core predicate for all one-way functions. In *STOC '89: Proceedings of the twenty-first annual ACM symposium on Theory of computing*, pages 25\u201332, New York, NY, USA, 1989. ACM.",
      "authors": [
        "Goldreich, Oded",
        "Levin, Leonid A."
      ],
      "title": "A hard-core predicate for all one-way functions",
      "year": "1989",
      "venue": "STOC '89: Proceedings of the twenty-first annual ACM symposium on Theory of computing",
      "volume": "",
      "pages": "25\u201332",
      "doi": "",
      "urls": [],
      "eprint_id": "",
      "arxiv_id": "",
      "isbn": "",
      "note": "",
      "entry_type": "inproceedings",
      "alpha_key": "GL89"
    },
    {
      "key": "[GMR89]",
      "raw_text": "Shafi Goldwasser, Silvio Micali, and Charles Rackoff. The knowledge complexity of interactive proof systems. *SIAM J. Comput.*, 18(1):186\u2013208, 1989.",
      "authors": [
        "Goldwasser, Shafi",
        "Micali, Silvio",
        "Rackoff, Charles"
      ],
      "title": "The knowledge complexity of interactive proof systems",
      "year": "1989",
      "venue": "SIAM J. Comput.",
      "volume": "18",
      "pages": "186\u2013208",
      "doi": "",
      "urls": [],
      "eprint_id": "",
      "arxiv_id": "",
      "isbn": "",
      "note": "",
      "entry_type": "article",
      "alpha_key": "GMR89"
    },
    {
      "key": "[GMW87]",
      "raw_text": "Oded Goldreich, Silvio Micali, and Avi Wigderson. How to play any mental game. In *STOC '87: Proceedings of the nineteenth annual ACM symposium on Theory of computing*, pages 218\u2013229, 1987.",
      "authors": [
        "Goldreich, Oded",
        "Micali, Silvio",
        "Wigderson, Avi"
      ],
      "title": "How to play any mental game",
      "year": "1987",
      "venue": "STOC '87: Proceedings of the nineteenth annual ACM symposium on Theory of computing",
      "volume": "",
      "pages": "218\u2013229",
      "doi": "",
      "urls": [],
      "eprint_id": "",
      "arxiv_id": "",
      "isbn": "",
      "note": "",
      "entry_type": "inproceedings",
      "alpha_key": "GMW87"
    },
    {
      "key": "[GO94]",
      "raw_text": "Oded Goldreich and Yair Oren. Definitions and properties of zero-knowledge proof systems. *Journal of Cryptology*, 7(1):1\u201332, December 1994.",
      "authors": [
        "Goldreich, Oded",
        "Oren, Yair"
      ],
      "title": "Definitions and properties of zero-knowledge proof systems",
      "year": "1994",
      "venue": "Journal of Cryptology",
      "volume": "7",
      "pages": "1\u201332",
      "doi": "",
      "urls": [],
      "eprint_id": "",
      "arxiv_id": "",
      "isbn": "",
      "note": "",
      "entry_type": "article",
      "alpha_key": "GO94"
    },
    {
      "key": "[Gol04]",
      "raw_text": "Oded Goldreich. *Foundations of Cryptography: Volume 2, Basic Applications*. Cambridge University Press, New York, NY, USA, 2004.",
      "authors": [
        "Goldreich, Oded"
      ],
      "title": "Foundations of Cryptography: Volume 2, Basic Applications",
      "year": "2004",
      "venue": "Cambridge University Press",
      "volume": "",
      "pages": "",
      "doi": "",
      "urls": [],
      "eprint_id": "",
      "arxiv_id": "",
      "isbn": "",
      "note": "",
      "entry_type": "book",
      "alpha_key": "Gol04"
    },
    {
      "key": "[GW11]",
      "raw_text": "Craig Gentry and Daniel Wichs. Separating succinct non-interactive arguments from all falsifiable assumptions. In *Proceedings of the 43rd Annual ACM Symposium on Theory of Computing*, pages 99\u2013108, 2011.",
      "authors": [
        "Gentry, Craig",
        "Wichs, Daniel"
      ],
      "title": "Separating succinct non-interactive arguments from all falsifiable assumptions",
      "year": "2011",
      "venue": "Proceedings of the 43rd Annual ACM Symposium on Theory of Computing",
      "volume": "",
      "pages": "99\u2013108",
      "doi": "",
      "urls": [],
      "eprint_id": "",
      "arxiv_id": "",
      "isbn": "",
      "note": "",
      "entry_type": "inproceedings",
      "alpha_key": "GW11"
    },
    {
      "key": "[HILL99]",
      "raw_text": "Johan Hastad, Russell Impagliazzo, Leonid A. Levin, and Michael Luby. A pseudorandom \u02da generator from any one-way function. *SIAM J. Comput.*, 28(4):1364\u20131396, 1999.",
      "authors": [
        "H\u00e5stad, Johan",
        "Impagliazzo, Russell",
        "Levin, Leonid A.",
        "Luby, Michael"
      ],
      "title": "A pseudorandom generator from any one-way function",
      "year": "1999",
      "venue": "SIAM J. Comput.",
      "volume": "28",
      "pages": "1364\u20131396",
      "doi": "",
      "urls": [],
      "eprint_id": "",
      "arxiv_id": "",
      "isbn": "",
      "note": "",
      "entry_type": "article",
      "alpha_key": "HILL99"
    },
    {
      "key": "[HK12]",
      "raw_text": "Shai Halevi and Yael Tauman Kalai. Smooth projective hashing and two-message oblivious transfer. *J. Cryptology*, 25(1):158\u2013193, 2012.",
      "authors": [
        "Halevi, Shai",
        "Kalai, Yael Tauman"
      ],
      "title": "Smooth projective hashing and two-message oblivious transfer",
      "year": "2012",
      "venue": "J. Cryptology",
      "volume": "25",
      "pages": "158\u2013193",
      "doi": "",
      "urls": [],
      "eprint_id": "",
      "arxiv_id": "",
      "isbn": "",
      "note": "",
      "entry_type": "article",
      "alpha_key": "HK12"
    },
    {
      "key": "[HT98]",
      "raw_text": "Satoshi Hada and Toshiaki Tanaka. On the existence of 3-round zero-knowledge protocols. In *Proceedings of the 18th Annual International Cryptology Conference*, pages 408\u2013423, 1998.",
      "authors": [
        "Hada, Satoshi",
        "Tanaka, Toshiaki"
      ],
      "title": "On the existence of 3-round zero-knowledge protocols",
      "year": "1998",
      "venue": "Proceedings of the 18th Annual International Cryptology Conference",
      "volume": "",
      "pages": "408\u2013423",
      "doi": "",
      "urls": [],
      "eprint_id": "",
      "arxiv_id": "",
      "isbn": "",
      "note": "",
      "entry_type": "inproceedings",
      "alpha_key": "HT98"
    },
    {
      "key": "[Kil92]",
      "raw_text": "Joe Kilian. A note on efficient zero-knowledge proofs and arguments. In *Proceedings of the 24th Annual ACM Symposium on Theory of Computing*, pages 723\u2013732, 1992.",
      "authors": [
        "Kilian, Joe"
      ],
      "title": "A note on efficient zero-knowledge proofs and arguments",
      "year": "1992",
      "venue": "Proceedings of the 24th Annual ACM Symposium on Theory of Computing",
      "volume": "",
      "pages": "723\u2013732",
      "doi": "",
      "urls": [],
      "eprint_id": "",
      "arxiv_id": "",
      "isbn": "",
      "note": "",
      "entry_type": "inproceedings",
      "alpha_key": "Kil92"
    },
    {
      "key": "[KRR]",
      "raw_text": "Yael Tauman Kalai, Ran Raz, and Ron D. Rothblum. Delegation for p. In *Announcement at STOC13*.",
      "authors": [
        "Kalai, Yael Tauman",
        "Raz, Ran",
        "Rothblum, Ron D."
      ],
      "title": "Delegation for p",
      "year": "",
      "venue": "Announcement at STOC13",
      "volume": "",
      "pages": "",
      "doi": "",
      "urls": [],
      "eprint_id": "",
      "arxiv_id": "",
      "isbn": "",
      "note": "",
      "entry_type": "misc",
      "alpha_key": ""
    },
    {
      "key": "[KRR13]",
      "raw_text": "Yael Tauman Kalai, Ran Raz, and Ron D. Rothblum. Delegation for bounded space. In *STOC*, pages 565\u2013574, 2013.",
      "authors": [
        "Kalai, Yael Tauman",
        "Raz, Ran",
        "Rothblum, Ron D."
      ],
      "title": "Delegation for bounded space",
      "year": "2013",
      "venue": "STOC",
      "volume": "",
      "pages": "565\u2013574",
      "doi": "",
      "urls": [],
      "eprint_id": "",
      "arxiv_id": "",
      "isbn": "",
      "note": "",
      "entry_type": "inproceedings",
      "alpha_key": "KRR13"
    },
    {
      "key": "[LS90]",
      "raw_text": "Dror Lapidot and Adi Shamir. Publicly verifiable non-interactive zero-knowledge proofs. In *CRYPTO*, pages 353\u2013365, 1990.",
      "authors": [
        "Lapidot, Dror",
        "Shamir, Adi"
      ],
      "title": "Publicly verifiable non-interactive zero-knowledge proofs",
      "year": "1990",
      "venue": "CRYPTO",
      "volume": "",
      "pages": "353\u2013365",
      "doi": "",
      "urls": [],
      "eprint_id": "",
      "arxiv_id": "",
      "isbn": "",
      "note": "",
      "entry_type": "inproceedings",
      "alpha_key": "LS90"
    },
    {
      "key": "[Nao03]",
      "raw_text": "Moni Naor. On cryptographic assumptions and challenges. In *Proceedings of the 23rd Annual International Cryptology Conference*, pages 96\u2013109, 2003.",
      "authors": [
        "Naor, Moni"
      ],
      "title": "On cryptographic assumptions and challenges",
      "year": "2003",
      "venue": "Proceedings of the 23rd Annual International Cryptology Conference",
      "volume": "",
      "pages": "96\u2013109",
      "doi": "",
      "urls": [],
      "eprint_id": "",
      "arxiv_id": "",
      "isbn": "",
      "note": "",
      "entry_type": "inproceedings",
      "alpha_key": "Nao03"
    },
    {
      "key": "[NP01]",
      "raw_text": "Moni Naor and Benny Pinkas. Efficient oblivious transfer protocols. In *SODA*, pages 448\u2013 457, 2001.",
      "authors": [
        "Naor, Moni",
        "Pinkas, Benny"
      ],
      "title": "Efficient oblivious transfer protocols",
      "year": "2001",
      "venue": "SODA",
      "volume": "",
      "pages": "448\u2013457",
      "doi": "",
      "urls": [],
      "eprint_id": "",
      "arxiv_id": "",
      "isbn": "",
      "note": "",
      "entry_type": "inproceedings",
      "alpha_key": "NP01"
    },
    {
      "key": "[OI07]",
      "raw_text": "Rafail Ostrovsky and William E. Skeith III. A survey of single-database private information retrieval: Techniques and applications. In *Public Key Cryptography*, pages 393\u2013411, 2007.",
      "authors": [
        "Ostrovsky, Rafail",
        "Skeith III, William E."
      ],
      "title": "A survey of single-database private information retrieval: Techniques and applications",
      "year": "2007",
      "venue": "Public Key Cryptography",
      "volume": "",
      "pages": "393\u2013411",
      "doi": "",
      "urls": [],
      "eprint_id": "",
      "arxiv_id": "",
      "isbn": "",
      "note": "",
      "entry_type": "inproceedings",
      "alpha_key": "OSI07"
    },
    {
      "key": "[OV12]",
      "raw_text": "Rafail Ostrovsky and Ivan Visconti. Simultaneous resettability from collision resistance. *Electronic Colloquium on Computational Complexity (ECCC)*, 2012.",
      "authors": [
        "Ostrovsky, Rafail",
        "Visconti, Ivan"
      ],
      "title": "Simultaneous resettability from collision resistance",
      "year": "2012",
      "venue": "Electronic Colloquium on Computational Complexity (ECCC)",
      "volume": "",
      "pages": "",
      "doi": "",
      "urls": [
        "https://eccc.weizmann.ac.il/report/2012/144/"
      ],
      "eprint_id": "",
      "arxiv_id": "",
      "isbn": "",
      "note": "",
      "entry_type": "article",
      "alpha_key": "OV12"
    },
    {
      "key": "[PW09]",
      "raw_text": "Rafael Pass and Hoeteck Wee. Black-box constructions of two-party protocols from oneway functions. In *TCC*, pages 403\u2013418, 2009.",
      "authors": [
        "Pass, Rafael",
        "Wee, Hoeteck"
      ],
      "title": "Black-box constructions of two-party protocols from oneway functions",
      "year": "2009",
      "venue": "TCC",
      "volume": "",
      "pages": "403\u2013418",
      "doi": "",
      "urls": [],
      "eprint_id": "",
      "arxiv_id": "",
      "isbn": "",
      "note": "",
      "entry_type": "inproceedings",
      "alpha_key": "PW09"
    },
    {
      "key": "[Yao86]",
      "raw_text": "Andrew Chi-Chih Yao. How to generate and exchange secrets (extended abstract). In *FOCS*, pages 162\u2013167, 1986.",
      "authors": [
        "Yao, Andrew Chi-Chih"
      ],
      "title": "How to generate and exchange secrets (extended abstract)",
      "year": "1986",
      "venue": "FOCS",
      "volume": "",
      "pages": "162\u2013167",
      "doi": "",
      "urls": [],
      "eprint_id": "",
      "arxiv_id": "",
      "isbn": "",
      "note": "",
      "entry_type": "inproceedings",
      "alpha_key": "Yao86"
    }
  ]
}
