{
  "backend": "marker",
  "converted_at": "2026-04-21T21:13:35.835962+00:00",
  "elapsed_seconds": 8600.97,
  "pdf_sha256": "94aa78109afacb4cd78b0281852e52096bad5dbb76f7d9a2883072e5b17bd515",
  "source_pdf": "2020_1469.pdf",
  "output_path": "2020_1469/2020_1469.md",
  "backend_version": "",
  "machine": {
    "hostname": "socs-MacBook-Pro.local",
    "os": "Darwin",
    "os_version": "25.4.0",
    "arch": "arm64",
    "python_version": "3.13.11",
    "cpu_count": 14,
    "provider": "",
    "gpu_count": 0,
    "gpu_name": "",
    "gpu_vram_mb": 0,
    "cuda_version": ""
  },
  "estimated_cost_usd": null
}
