{
  "paper_id": "2009_265",
  "references": [
    {
      "key": "[1]",
      "raw_text": "Andreeva, E., Neven, G., Preneel, B., Shrimpton, T.: Seven-property-preserving hashing: ROX. In: Kurosawa, K. (ed.) ASIACRYPT'2007. LNCS 4833, pp. 130-146. Springer, 2007.",
      "authors": [
        "Andreeva, E.",
        "Neven, G.",
        "Preneel, B.",
        "Shrimpton, T."
      ],
      "title": "Seven-property-preserving hashing: ROX",
      "year": "2007",
      "venue": "ASIACRYPT",
      "volume": "4833",
      "pages": "130-146",
      "doi": "",
      "urls": [],
      "eprint_id": "",
      "arxiv_id": "",
      "isbn": "",
      "note": "",
      "entry_type": "inproceedings",
      "alpha_key": "ANPS07"
    },
    {
      "key": "[2]",
      "raw_text": "Bellare, M., Ristenpart, T.: Multi-property-preserving hash domain extension: The EMD transform. In: Lai, X., Chen, K. (eds.) ASIACRYPT'2006. LNCS 4284, pp. 299-314. Springer, 2006.",
      "authors": [
        "Bellare, M.",
        "Ristenpart, T."
      ],
      "title": "Multi-property-preserving hash domain extension: The EMD transform",
      "year": "2006",
      "venue": "ASIACRYPT",
      "volume": "4284",
      "pages": "299-314",
      "doi": "",
      "urls": [],
      "eprint_id": "",
      "arxiv_id": "",
      "isbn": "",
      "note": "",
      "entry_type": "inproceedings",
      "alpha_key": "BR06"
    },
    {
      "key": "[3]",
      "raw_text": "M. Bellare and T. Ristenpart. Hash Functions in the Dedicated-key Setting: Design Choices and MPP Transforms. In: ICALP'07, LNCS 4596, pp. 339-410. Springer, 2007.",
      "authors": [
        "Bellare, M.",
        "Ristenpart, T."
      ],
      "title": "Hash Functions in the Dedicated-key Setting: Design Choices and MPP Transforms",
      "year": "2007",
      "venue": "ICALP",
      "volume": "4596",
      "pages": "339-410",
      "doi": "",
      "urls": [],
      "eprint_id": "",
      "arxiv_id": "",
      "isbn": "",
      "note": "",
      "entry_type": "inproceedings",
      "alpha_key": "BR07"
    },
    {
      "key": "[4]",
      "raw_text": "G. Bertoni, J. Daemen, M. Peeters, G. Van Assche: On the indifferentiability of the sponge construction. In: Smart, N. (ed.) EUROCRYPT'2008. LNCS 4965, pp. 181-197. 2008.",
      "authors": [
        "Bertoni, G.",
        "Daemen, J.",
        "Peeters, M.",
        "Van Assche, G."
      ],
      "title": "On the indifferentiability of the sponge construction",
      "year": "2008",
      "venue": "EUROCRYPT",
      "volume": "4965",
      "pages": "181-197",
      "doi": "",
      "urls": [],
      "eprint_id": "",
      "arxiv_id": "",
      "isbn": "",
      "note": "",
      "entry_type": "inproceedings",
      "alpha_key": "BDPVA08"
    },
    {
      "key": "[5]",
      "raw_text": "J. Black, P. Rogaway, and T. Shrimpton. Black-box analysis of the blockcipher- based hash function constructions from PGV. In Crypto2002, LNCS 2442, pp. 320-335. Springer, 2002.",
      "authors": [
        "Black, J.",
        "Rogaway, P.",
        "Shrimpton, T."
      ],
      "title": "Black-box analysis of the blockcipher-based hash function constructions from PGV",
      "year": "2002",
      "venue": "Crypto",
      "volume": "2442",
      "pages": "320-335",
      "doi": "",
      "urls": [],
      "eprint_id": "",
      "arxiv_id": "",
      "isbn": "",
      "note": "",
      "entry_type": "inproceedings",
      "alpha_key": "BRS02"
    },
    {
      "key": "[6]",
      "raw_text": "B. O. Brachtl, D. Coppersmith, M.M. Hyden, S.M. Matyas, C.H. Meyer, J. Oseas, S. Pilpel and M. Schilling. Data Authentication Using Modification Detection Codes Based on a Public One Way Encryption Function. U.S. Patent Number 4,908,861, March 13, 1990.",
      "authors": [
        "Brachtl, B. O.",
        "Coppersmith, D.",
        "Hyden, M. M.",
        "Matyas, S. M.",
        "Meyer, C. H.",
        "Oseas, J.",
        "Pilpel, S.",
        "Schilling, M."
      ],
      "title": "Data Authentication Using Modification Detection Codes Based on a Public One Way Encryption Function",
      "year": "1990",
      "venue": "U.S. Patent",
      "volume": "",
      "pages": "",
      "doi": "",
      "urls": [],
      "eprint_id": "",
      "arxiv_id": "",
      "isbn": "",
      "note": "Number 4,908,861",
      "entry_type": "misc",
      "alpha_key": "BCH+90"
    },
    {
      "key": "[7]",
      "raw_text": "D. H. Chang, S. J. Lee, M. Nandi and M. Yung. Indifferentiable Security Analysis of Popular Hash Functions with Prefix-Free Padding. In: X. Lai and K. Chen(eds): ASIACRYPT'2006, LNCS 4284, pp. 283-298. Springer, 2006.",
      "authors": [
        "Chang, D. H.",
        "Lee, S. J.",
        "Nandi, M.",
        "Yung, M."
      ],
      "title": "Indifferentiable Security Analysis of Popular Hash Functions with Prefix-Free Padding",
      "year": "2006",
      "venue": "ASIACRYPT",
      "volume": "4284",
      "pages": "283-298",
      "doi": "",
      "urls": [],
      "eprint_id": "",
      "arxiv_id": "",
      "isbn": "",
      "note": "",
      "entry_type": "inproceedings",
      "alpha_key": "CLNY06"
    },
    {
      "key": "[8]",
      "raw_text": "D. H. Chang and M. Nandi. Improved Indifferentiability Security Analysis of chopMD Hash Function. In: K. Nyberg(ed.): FSE'2008, LNCS 5086, pp. 429-443, Springer, 2008.",
      "authors": [
        "Chang, D. H.",
        "Nandi, M."
      ],
      "title": "Improved Indifferentiability Security Analysis of chopMD Hash Function",
      "year": "2008",
      "venue": "FSE",
      "volume": "5086",
      "pages": "429-443",
      "doi": "",
      "urls": [],
      "eprint_id": "",
      "arxiv_id": "",
      "isbn": "",
      "note": "",
      "entry_type": "inproceedings",
      "alpha_key": "CN08"
    },
    {
      "key": "[9]",
      "raw_text": "J. S. Coron, Y. Dodis, C. Malinaud and P. Puniya. Merkle-Damgard Revisited: How to Construct a Hash Function. In: CRYPTO'05, LNCS 3621, pp. 21-39. 2005.",
      "authors": [
        "Coron, J. S.",
        "Dodis, Y.",
        "Malinaud, C.",
        "Puniya, P."
      ],
      "title": "Merkle-Damgard Revisited: How to Construct a Hash Function",
      "year": "2005",
      "venue": "CRYPTO",
      "volume": "3621",
      "pages": "21-39",
      "doi": "",
      "urls": [],
      "eprint_id": "",
      "arxiv_id": "",
      "isbn": "",
      "note": "",
      "entry_type": "inproceedings",
      "alpha_key": "CDMP05"
    },
    {
      "key": "[10]",
      "raw_text": "J. S. Coron, Y. Dodis, C. Malinaud and P. Puniya. Merkle-Damgard Revisited: How to Construct a Hash Function (Full Version). In http://people.csail.mit.edu/dodis/ps/merkle.ps. 2007. A preliminary version was accepted by Crypto'05, LNCS 3621, pp. 21-39. 2005.",
      "authors": [
        "Coron, J. S.",
        "Dodis, Y.",
        "Malinaud, C.",
        "Puniya, P."
      ],
      "title": "Merkle-Damgard Revisited: How to Construct a Hash Function (Full Version)",
      "year": "2007",
      "venue": "",
      "volume": "",
      "pages": "",
      "doi": "",
      "urls": [
        "http://people.csail.mit.edu/dodis/ps/merkle.ps"
      ],
      "eprint_id": "",
      "arxiv_id": "",
      "isbn": "",
      "note": "A preliminary version was accepted by Crypto'05, LNCS 3621, pp. 21-39. 2005",
      "entry_type": "misc",
      "alpha_key": "CDMP07"
    },
    {
      "key": "[11]",
      "raw_text": "J. S. Coron, J. Patarin, and Y. Seurin. The random oracle model and the ideal cipher model are equivalent. In D. Wagner(ed.), CRYPTO'2008, LNCS 5157, pp. 1-20. Springer, 2008.",
      "authors": [
        "Coron, J. S.",
        "Patarin, J.",
        "Seurin, Y."
      ],
      "title": "The random oracle model and the ideal cipher model are equivalent",
      "year": "2008",
      "venue": "CRYPTO",
      "volume": "5157",
      "pages": "1-20",
      "doi": "",
      "urls": [],
      "eprint_id": "",
      "arxiv_id": "",
      "isbn": "",
      "note": "",
      "entry_type": "inproceedings",
      "alpha_key": "CPS08"
    },
    {
      "key": "[12]",
      "raw_text": "I. Damgard. A Design Principle for Hash Functions, In:Cyrpto'89, LNCS 435, pp. 416-427. Springer, 1989.",
      "authors": [
        "Damgard, I."
      ],
      "title": "A Design Principle for Hash Functions",
      "year": "1989",
      "venue": "Crypto",
      "volume": "435",
      "pages": "416-427",
      "doi": "",
      "urls": [],
      "eprint_id": "",
      "arxiv_id": "",
      "isbn": "",
      "note": "",
      "entry_type": "inproceedings",
      "alpha_key": "Dam89"
    },
    {
      "key": "[13]",
      "raw_text": "Y. Dodis, L. Reyzin, R. L. Rivest and E. Shen. Indifferentiability of Permutation-Based Compression Functions and Tree-Based Modes of Operation, with Applications to MD6. FSE'09, Appear soon.",
      "authors": [
        "Dodis, Y.",
        "Reyzin, L.",
        "Rivest, R. L.",
        "Shen, E."
      ],
      "title": "Indifferentiability of Permutation-Based Compression Functions and Tree-Based Modes of Operation, with Applications to MD6",
      "year": "",
      "venue": "FSE",
      "volume": "",
      "pages": "",
      "doi": "",
      "urls": [],
      "eprint_id": "",
      "arxiv_id": "",
      "isbn": "",
      "note": "Appear soon",
      "entry_type": "inproceedings",
      "alpha_key": ""
    },
    {
      "key": "[14]",
      "raw_text": "Y. Dodis, T. Ristenpart, and T. Shrimpton. Salvaging Merkle-Damgard for Practical Applications. In: Euro-Crypt'09, LNCS 5479, pp. 371-388. Springer.",
      "authors": [
        "Dodis, Y.",
        "Ristenpart, T.",
        "Shrimpton, T."
      ],
      "title": "Salvaging Merkle-Damgard for Practical Applications",
      "year": "",
      "venue": "Euro-Crypt",
      "volume": "5479",
      "pages": "371-388",
      "doi": "",
      "urls": [],
      "eprint_id": "",
      "arxiv_id": "",
      "isbn": "",
      "note": "",
      "entry_type": "inproceedings",
      "alpha_key": ""
    },
    {
      "key": "[15]",
      "raw_text": "Z. Gong, X. Lai, and K. Chen. A Synthetic Indifferentiability Analysis of Some Block-Cipher-Based Hash Functions. Designs, Codes and Cryptography, Springer. 48(3), Sept 2008.",
      "authors": [
        "Gong, Z.",
        "Lai, X.",
        "Chen, K."
      ],
      "title": "A Synthetic Indifferentiability Analysis of Some Block-Cipher-Based Hash Functions",
      "year": "2008",
      "venue": "Designs, Codes and Cryptography",
      "volume": "48",
      "pages": "",
      "doi": "",
      "urls": [],
      "eprint_id": "",
      "arxiv_id": "",
      "isbn": "",
      "note": "3, Sept 2008",
      "entry_type": "article",
      "alpha_key": "GLC08"
    },
    {
      "key": "[16]",
      "raw_text": "S. Hirose. Some Plausible Constructions of Double-Length Hash Functions. In: FSE'06, LNCS 4047, pp. 210- 225. Springer, 2006.",
      "authors": [
        "Hirose, S."
      ],
      "title": "Some Plausible Constructions of Double-Length Hash Functions",
      "year": "2006",
      "venue": "FSE",
      "volume": "4047",
      "pages": "210-225",
      "doi": "",
      "urls": [],
      "eprint_id": "",
      "arxiv_id": "",
      "isbn": "",
      "note": "",
      "entry_type": "inproceedings",
      "alpha_key": "Hir06"
    },
    {
      "key": "[17]",
      "raw_text": "S. Hirose, J. Park, and A. Yun. A Simple Variant of the Merkle-Damgard Scheme with a Permutation. In: ASIACRYPT'07, LNCS vol. 4833, pp. 113-129. Springer, 2007.",
      "authors": [
        "Hirose, S.",
        "Park, J.",
        "Yun, A."
      ],
      "title": "A Simple Variant of the Merkle-Damgard Scheme with a Permutation",
      "year": "2007",
      "venue": "ASIACRYPT",
      "volume": "4833",
      "pages": "113-129",
      "doi": "",
      "urls": [],
      "eprint_id": "",
      "arxiv_id": "",
      "isbn": "",
      "note": "",
      "entry_type": "inproceedings",
      "alpha_key": "HPY07"
    },
    {
      "key": "[18]",
      "raw_text": "H. Kuwakado , M. Morii: Indifferentiability of single-block-length and rate-1 compression functions. IEICE Trans Fundamentals, vol.e90-A, pp. 2301-2308. 2007.",
      "authors": [
        "Kuwakado, H.",
        "Morii, M."
      ],
      "title": "Indifferentiability of single-block-length and rate-1 compression functions",
      "year": "2007",
      "venue": "IEICE Trans Fundamentals",
      "volume": "e90-A",
      "pages": "2301-2308",
      "doi": "",
      "urls": [],
      "eprint_id": "",
      "arxiv_id": "",
      "isbn": "",
      "note": "",
      "entry_type": "article",
      "alpha_key": "KM07"
    },
    {
      "key": "[19]",
      "raw_text": "U. Maurer, R. Renner, and C. Holenstein. Indifferentiability, Impossibility Results on Reductions, and Applications to the Random Oracle Methodology. In: *TCC*'2004, LNCS 2951, pp. 21-39. Springer, 2004.",
      "authors": [
        "Maurer, U.",
        "Renner, R.",
        "Holenstein, C."
      ],
      "title": "Indifferentiability, Impossibility Results on Reductions, and Applications to the Random Oracle Methodology",
      "year": "2004",
      "venue": "TCC",
      "volume": "2951",
      "pages": "21-39",
      "doi": "",
      "urls": [],
      "eprint_id": "",
      "arxiv_id": "",
      "isbn": "",
      "note": "",
      "entry_type": "inproceedings",
      "alpha_key": "MRH04"
    },
    {
      "key": "[20]",
      "raw_text": "U. Maurer and S. Tessaro. Domain Extension of Public Random Functions: Beyond the Birthday Barrier. In: Menezes, A. (ed.) *CRYPTO* '2007. LNCS 4622, pp. 187-204. Springer, 2007",
      "authors": [
        "Maurer, U.",
        "Tessaro, S."
      ],
      "title": "Domain Extension of Public Random Functions: Beyond the Birthday Barrier",
      "year": "2007",
      "venue": "CRYPTO",
      "volume": "4622",
      "pages": "187-204",
      "doi": "",
      "urls": [],
      "eprint_id": "",
      "arxiv_id": "",
      "isbn": "",
      "note": "",
      "entry_type": "inproceedings",
      "alpha_key": "MT07"
    },
    {
      "key": "[21]",
      "raw_text": "R.C. Merkle. One way hash functions and DES, In: Crypto'89, LNCS 435, pp. 428-446. Springer, 1989.",
      "authors": [
        "Merkle, R. C."
      ],
      "title": "One way hash functions and DES",
      "year": "1989",
      "venue": "Crypto",
      "volume": "435",
      "pages": "428-446",
      "doi": "",
      "urls": [],
      "eprint_id": "",
      "arxiv_id": "",
      "isbn": "",
      "note": "",
      "entry_type": "inproceedings",
      "alpha_key": "Mer89"
    },
    {
      "key": "[22]",
      "raw_text": "B. Preneel, R. Govaerts and J. Vandewalle. Hash functions based on block ciphers: A synthetic approach. In: *CRYPTO'93*, LNCS 773, pp. 368-378. Springer, 1994.",
      "authors": [
        "Preneel, B.",
        "Govaerts, R.",
        "Vandewalle, J."
      ],
      "title": "Hash functions based on block ciphers: A synthetic approach",
      "year": "1994",
      "venue": "CRYPTO",
      "volume": "773",
      "pages": "368-378",
      "doi": "",
      "urls": [],
      "eprint_id": "",
      "arxiv_id": "",
      "isbn": "",
      "note": "",
      "entry_type": "inproceedings",
      "alpha_key": "PGV94"
    },
    {
      "key": "[23]",
      "raw_text": "X. Wang, Y. Yin and H. Yu. Finding Collision in the Full SHA-1. In: *CRYPTO'05*, LNCS 3621, pp. 17-36. Springer, 2005.",
      "authors": [
        "Wang, X.",
        "Yin, Y.",
        "Yu, H."
      ],
      "title": "Finding Collision in the Full SHA-1",
      "year": "2005",
      "venue": "CRYPTO",
      "volume": "3621",
      "pages": "17-36",
      "doi": "",
      "urls": [],
      "eprint_id": "",
      "arxiv_id": "",
      "isbn": "",
      "note": "",
      "entry_type": "inproceedings",
      "alpha_key": "WYY05"
    },
    {
      "key": "[24]",
      "raw_text": "X. Wang and H. Yu. How to Break MD5 and Other Hash Functions. In: *EUROCRYPT'05*, LNCS 3494, pp. 19-35. Springer, 2005.",
      "authors": [
        "Wang, X.",
        "Yu, H."
      ],
      "title": "How to Break MD5 and Other Hash Functions",
      "year": "2005",
      "venue": "EUROCRYPT",
      "volume": "3494",
      "pages": "19-35",
      "doi": "",
      "urls": [],
      "eprint_id": "",
      "arxiv_id": "",
      "isbn": "",
      "note": "",
      "entry_type": "inproceedings",
      "alpha_key": "WY05"
    }
  ]
}
