{
  "backend": "marker",
  "converted_at": "2026-03-17T08:01:52.098537+00:00",
  "elapsed_seconds": 205.43,
  "pdf_sha256": "f1e1430d354ebfd84e752e0250d27b56d06dfdf041c7691b5e1096985cce9f81",
  "source_pdf": "2020_716.pdf",
  "output_path": "2020_716/2020_716.md",
  "backend_version": "",
  "machine": {
    "hostname": "socs-MacBook-Pro.local",
    "os": "Darwin",
    "os_version": "25.3.0",
    "arch": "arm64",
    "python_version": "3.13.11",
    "cpu_count": 14,
    "provider": "",
    "gpu_count": 0,
    "gpu_name": "",
    "gpu_vram_mb": 0,
    "cuda_version": ""
  },
  "estimated_cost_usd": null
}
