{
  "backend": "marker",
  "converted_at": "2026-02-26T23:04:04.604542+00:00",
  "elapsed_seconds": 710.05,
  "pdf_sha256": "602e6f0c7bd218a1308951351504ac12b809991937a3fdb2ede22799f9385f0e",
  "source_pdf": "2021_1152.pdf",
  "output_path": "2021_1152/2021_1152/2021_1152.md",
  "backend_version": "",
  "machine": {
    "hostname": "Mac.bbrouter",
    "os": "Darwin",
    "os_version": "25.2.0",
    "arch": "arm64",
    "python_version": "3.13.11",
    "cpu_count": 14,
    "provider": "",
    "gpu_count": 0,
    "gpu_name": "",
    "gpu_vram_mb": 0,
    "cuda_version": ""
  }
}
