{
  "backend": "marker",
  "converted_at": "2026-04-02T17:58:50.799926+00:00",
  "elapsed_seconds": 555.91,
  "pdf_sha256": "d1ff51395a97cdf3278b3b9f7821a1c55e4d88c1f6aff9222abfdc78aa6d9835",
  "source_pdf": "2018_1247.pdf",
  "output_path": "2018_1247/2018_1247.md",
  "backend_version": "",
  "machine": {
    "hostname": "mac.home",
    "os": "Darwin",
    "os_version": "25.4.0",
    "arch": "arm64",
    "python_version": "3.13.11",
    "cpu_count": 14,
    "provider": "",
    "gpu_count": 0,
    "gpu_name": "",
    "gpu_vram_mb": 0,
    "cuda_version": ""
  },
  "estimated_cost_usd": null
}
